Workbook

Sheet How_To_Use
A1: WEALTH ADVISORY v2.0 — COMPLETE USER GUIDE
A2: 25 Features | Siddharth Tiwari | Read fully before using
A4: 1. WORKBOOK OVERVIEW — 13 SHEETS
B5: Sheet | C5: Purpose | D5: Key Features
B6: How_To_Use | C6: Complete guide | D6: Step-by-step instructions, column reference
B7: Assumptions_Config | C7: Global settings | D7: Inflation, tax, horizon, types, scenarios, risk scores
B8: Investment_Input | C8: Investment entry | D8: One row per investment, auto-lookups, validations
B9: Debt_Tracker | C9: Loan tracking | D9: Home/car/personal loans, EMIs, prepayment analysis
B10: Income_Expenses | C10: Cash flow | D10: Income sources, expense categories, savings rate
B11: Major_Expenses | C11: Future expenses | D11: Goal-linked, inflation-adjusted future costs
B12: Goals_Tracker | C12: Goal planning | D12: Link investments to goals, shortfall analysis
B13: Insurance_Summary | C13: Insurance audit | D13: Life/health/vehicle cover, gap analysis
B14: Helper_Calcs | C14: Calculations | D14: Projections, aggregation, scenarios, scores
B15: Advisor_Dashboard | C15: Advisor view | D15: Full analytics, KPIs, charts, allocation, scenarios
B16: Client_Dashboard | C16: Client view | D16: Executive summary, polished, print-ready
... B18: What_If_Builder | C18: Scenario builder | D18: Interactive what-if comparisons
A20: 2. CELL CONVENTIONS
B21: 🟡 GOLD CELLS | E21: Editable input — type freely
B22: 🔵 BLUE-GREY CELLS | E22: Auto-calculated formula — don't edit
B23: ⬜ WHITE/GREY | E23: Structural/locked — headers, labels
A25: 3. STEP-BY-STEP WORKFLOW
B26: STEP 1: Assumptions_Config | E26: Set inflation (D5), tax (D6), display unit (D7), horizon (D8), reinvest rate (D9). Review type mappings & scenarios.
B27: STEP 2: Income_Expenses | E27: Enter all income sources and monthly expenses. This calculates your investable surplus.
B28: STEP 3: Debt_Tracker | E28: Enter all loans. TRUE net worth = Assets minus Liabilities.
B29: STEP 4: Investment_Input | E29: One row per investment. Set type, current value, monthly contribution, return, tenure, tax flag.
B30: STEP 5: Insurance_Summary | E30: Enter life, health, vehicle insurance. Model checks if coverage is adequate.
B31: STEP 6: Goals_Tracker | E31: Define goals (retirement, education, house). Link investments. See funding status.
B32: STEP 7: Major_Expenses | E32: Enter future expenses. These reduce projected wealth in the relevant year.
B33: STEP 8: What_If_Builder | E33: Test scenarios like increasing SIP or adding lump sums.
B34: STEP 9: View Dashboards | E34: Advisor_Dashboard for detailed analysis. Client_Dashboard for presentations.
B35: STEP 10: Financial_Scorecard | E35: Review 10-dimension health score and action items.
A37: 4. ALL 25 FEATURES
B38: 1. Multi-investment tracking (unlimited rows per type)
B39: 2. Inflation-adjusted projections (nominal + real)
B40: 3. Tax-adjusted outputs (per-row tax flag)
B41: 4. 5 Scenario analysis (optimistic to conservative)
B42: 5. SIP step-up compounding
B43: 6. Post-maturity reinvestment logic
B44: 7. Major future expenses with inflation
B45: 8. Year-by-year projection grid + charts
B46: 9. Equity vs Debt allocation analysis
B47: 10. Display unit toggle (₹/Lakhs/Crores/Millions)
B48: 11. Goal-based tracking with shortfall analysis
B49: 12. Cash flow / liquidity timeline
... B62: 25. Action item / recommendation tracker

Sheet Assumptions_Config
A1: ASSUMPTIONS & CONFIGURATION
A2: Edit GOLD cells | Blue-grey = auto | Drives all calculations
A4: GLOBAL ASSUMPTIONS
C5: Inflation Rate (%) | D5: 0.1 | E5: ← Annual CPI inflation
C6: Effective Tax Rate (%) | D6: 0.25 | E6: ← Tax on investment gains
C7: Display Unit | D7: Lakhs | E7: ← ₹/Lakhs/Crores/Millions
C8: Forecast Horizon (Years) | D8: 15 | E8: ← 5/10/15/20/25/30
C9: Default Reinvest Rate (%) | D9: 0.065 | E9: ← Post-maturity rate
C10: Forecast Start Year | D10: 2026 | E10: ← Current year
C11: Risk-Free Rate (%) | D11: 0.07 | E11: ← FD/Govt bond rate
C12: Monthly Expenses (₹) | D12: 50000 | E12: ← For emergency fund calc
C13: Emergency Fund Months | D13: 12 | E13: ← Target months of expenses
C14: Retirement Age | D14: 45 | E14: ← Planned retirement age
C15: Current Age | D15: 35 | E15: ← Client's current age
C16: Life Expectancy | D16: 60 | E16: ← For retirement corpus calc
C17: Annual Income (₹) | D17: 1800000 | E17: ← Gross annual income
C18: Client Name | D18: [Enter Client Name]
A20: SCENARIO ASSUMPTIONS
C21: Scenario | D21: Multiplier | E21: Inf Override | F21: Tax Override | G21: Eff Inf | H21: Eff Tax | I21: Description
C22: Optimistic | D22: 1.15 | G22: =IF(E22="",$D$5,E22) -> 0.1 | H22: =IF(F22="",$D$6,F22) -> 0.25 | I22: Best-case
C23: Mod. Optimistic | D23: 1.07 | G23: =IF(E23="",$D$5,E23) -> 0.1 | H23: =IF(F23="",$D$6,F23) -> 0.25 | I23: Above-avg
C24: Base Case | D24: 1 | G24: =IF(E24="",$D$5,E24) -> 0.1 | H24: =IF(F24="",$D$6,F24) -> 0.25 | I24: Expected
C25: Mod. Conservative | D25: 0.9 | G25: =IF(E25="",$D$5,E25) -> 0.1 | H25: =IF(F25="",$D$6,F25) -> 0.25 | I25: Below-avg
C26: Conservative | D26: 0.8 | G26: =IF(E26="",$D$5,E26) -> 0.1 | H26: =IF(F26="",$D$6,F26) -> 0.25 | I26: Worst-case
A29: INVESTMENT TYPE MASTER (with Risk Scores)
C30: Type | D30: Asset Class | E30: Bucket | F30: Return % | G30: Compounding | H30: Risk(1-10) | I30: Volatility
C31: SIP | D31: Equity | E31: Equity | F31: 0.12 | G31: Monthly | H31: 7 | I31: High
C32: Stocks | D32: Equity | E32: Equity | F32: 0.12 | G32: Annually | H32: 8 | I32: High
C33: FD | D33: Debt | E33: Debt | F33: 0.065 | G33: Quarterly | H33: 2 | I33: Low
C34: RD | D34: Debt | E34: Debt | F34: 0.065 | G34: Quarterly | H34: 2 | I34: Low
C35: PF | D35: Retirement | E35: Debt | F35: 0.081 | G35: Annually | H35: 1 | I35: Very Low
C36: PPF | D36: Retirement | E36: Debt | F36: 0.071 | G36: Annually | H36: 1 | I36: Very Low
C37: NPS | D37: Retirement | E37: Equity | F37: 0.1 | G37: Annually | H37: 5 | I37: Medium
C38: Savings Account | D38: Cash | E38: Debt | F38: 0.04 | G38: Quarterly | H38: 1 | I38: Very Low
C39: Gold | D39: Real Asset | E39: Other | F39: 0.08 | G39: Annually | H39: 4 | I39: Medium
C40: Silver | D40: Real Asset | E40: Other | F40: 0.07 | G40: Annually | H40: 5 | I40: Medium
C41: Land | D41: Real Asset | E41: Other | F41: 0.1 | G41: Annually | H41: 6 | I41: Med-High
C42: Crypto | D42: Alternative | E42: Other | F42: 0.15 | G42: Annually | H42: 10 | I42: Very High
C43: Others | D43: Other | E43: Other | F43: 0.06 | G43: Annually | H43: 5 | I43: Medium
A46: STRESS TEST SCENARIOS
C47: Event | D47: Equity Impact | E47: Debt Impact | F47: Gold Impact | G47: Description
C48: 2008 Crisis | D48: -0.52 | E48: -0.05 | F48: 0.25 | G48: Global financial crisis
C49: COVID 2020 | D49: -0.38 | E49: -0.02 | F49: 0.15 | G49: Pandemic crash
C50: 2013 Taper | D50: -0.25 | E50: -0.08 | F50: -0.1 | G50: Fed taper tantrum
C51: Inflation Spike | D51: -0.15 | E51: -0.1 | F51: 0.2 | G51: High inflation period
C52: Custom | D52: -0.3 | E52: -0.05 | F52: 0.1 | G52: User-defined stress
A55: TARGET ALLOCATION (for Rebalancing)
C56: Bucket | D56: Target % | E56: Notes
C57: Equity | D57: 0.7 | E57: Editable
C58: Debt | D58: 0.1 | E58: Editable
C59: Other | D59: 0.2 | E59: Editable
A62: MODEL DRIVERS — scenario and advisory assumptions
C63: Goal Growth Rate (%) | D63: 0.1 | E63: ← Used in goal funding projections
C64: What-If Return Rate (%) | D64: 0.12 | E64: ← Used in scenario builder and recovery math
C65: Safe Withdrawal Rate (%) | D65: 0.03 | E65: ← Used in retirement corpus adequacy
C66: Early Retirement Impact (%) | D66: -0.12 | E66: ← Applied to corpus in retire-early scenario
C67: Higher Inflation Impact (%) | D67: -0.07 | E67: ← Applied when inflation assumption worsens
C68: Step-Up Improvement Impact (%) | D68: 0.05 | E68: ← Applied when SIP step-up improves

Sheet Investment_Input
A1: INVESTMENT INPUT — LINE ITEM ENTRY
A2: One row per investment | Gold=edit | Blue-grey=auto | Tab to add rows
A3: PORTFOLIO SUMMARY
A4: Total Current Value | C4: =SUMPRODUCT((B9:B28="Yes")*I9:I28) -> 4115000 | E4: Monthly→Equity | G4: =SUMPRODUCT((B9:B28="Yes")*(G9:G28="Equity")*J9:J28) -> 17000 | H4: Wtd Risk Score | J4: =IF(SUMPRODUCT((B9:B28="Yes")*I9:I28)=0,0,SUMPRODUCT((B9:B28="Yes")*I9:I28*X9:X28)/SUMPRODUCT((B9:B28="Yes")*I9:I28)) -> 5.2867558
A5: Total Monthly SIP | C5: =SUMPRODUCT((B9:B28="Yes")*(H9:H28="Recurring")*J9:J28) -> 27000 | E5: Monthly→Debt | G5: =SUMPRODUCT((B9:B28="Yes")*(G9:G28="Debt")*J9:J28) -> 10000 | H5: Max Concentration% | J5: =IF(SUMPRODUCT((B9:B28="Yes")*I9:I28)=0,0,MAX(I9:I28)/SUMPRODUCT((B9:B28="Yes")*I9:I28)) -> 0.48602673
A6: Active Investments | C6: =COUNTIF(B9:B28,"Yes") -> 12 | E6: Monthly→Other | G6: =SUMPRODUCT((B9:B28="Yes")*(G9:G28="Other")*J9:J28) -> 0
A8: ID | B8: Active? | C8: Type | D8: Label | E8: Member | F8: Asset Class | G8: Bucket | H8: One-Time/Rec | I8: Current Value | J8: Monthly | K8: Return % | L8: Override? | M8: Eff Return | N8: Step-Up % | O8: Compounding | P8: Periods/Yr | Q8: Tenure | R8: Unit | S8: Tenure(Yrs) | T8: Rem Tenure | U8: Eff Rem | V8: Reinv Ovrd | W8: Eff Reinv | X8: Risk Score | Y8: Start Dt | Z8: Mat Dt | AA8: Tax? | AB8: Notes
A9: 1 | B9: Yes | C9: SIP | D9: Axis Bluechip SIP | E9: Self | F9: =IFERROR(VLOOKUP(C9,Assumptions_Config!$C$31:$I$43,2,FALSE),"Other") -> Equity | G9: =IFERROR(VLOOKUP(C9,Assumptions_Config!$C$31:$I$43,3,FALSE),"Other") -> Equity | H9: Recurring | I9: 125000 | J9: 5000 | K9: 0.12 | L9: No | M9: =IF(L9="Yes",K9,IFERROR(VLOOKUP(C9,Assumptions_Config!$C$31:$I$43,4,FALSE),K9)) -> 0.12 | N9: 0.1 | O9: Monthly | P9: =IFERROR(_xludf.SWITCH(O9,"Monthly",12,"Quarterly",4,"Half-Yearly",2,"Annually",1),1) -> 1 | Q9: 15 | R9: Years | S9: =IF(R9="Months",Q9/12,Q9) -> 15 | T9: 15 | U9: =IF(AND(T9<>"",T9>0),T9,S9) -> 15 | W9: =IF(AND(V9<>"",V9>0),V9,Assumptions_Config!$D$9) -> 0.065 | X9: =IFERROR(VLOOKUP(C9,Assumptions_Config!$C$31:$I$43,6,FALSE),5) -> 7 | AA9: Yes | AB9: Long-term
A10: 2 | B10: Yes | C10: SIP | D10: HDFC Mid-Cap SIP | E10: Self | F10: =IFERROR(VLOOKUP(C10,Assumptions_Config!$C$31:$I$43,2,FALSE),"Other") -> Equity | G10: =IFERROR(VLOOKUP(C10,Assumptions_Config!$C$31:$I$43,3,FALSE),"Other") -> Equity | H10: Recurring | I10: 80000 | J10: 3000 | K10: 0.14 | L10: Yes | M10: =IF(L10="Yes",K10,IFERROR(VLOOKUP(C10,Assumptions_Config!$C$31:$I$43,4,FALSE),K10)) -> 0.14 | N10: 0.05 | O10: Monthly | P10: =IFERROR(_xludf.SWITCH(O10,"Monthly",12,"Quarterly",4,"Half-Yearly",2,"Annually",1),1) -> 1 | Q10: 10 | R10: Years | S10: =IF(R10="Months",Q10/12,Q10) -> 10 | T10: 10 | U10: =IF(AND(T10<>"",T10>0),T10,S10) -> 10 | W10: =IF(AND(V10<>"",V10>0),V10,Assumptions_Config!$D$9) -> 0.065 | X10: =IFERROR(VLOOKUP(C10,Assumptions_Config!$C$31:$I$43,6,FALSE),5) -> 7 | AA10: Yes | AB10: Mid-cap
A11: 3 | B11: Yes | C11: FD | D11: SBI FD #1 | E11: Self | F11: =IFERROR(VLOOKUP(C11,Assumptions_Config!$C$31:$I$43,2,FALSE),"Other") -> Debt | G11: =IFERROR(VLOOKUP(C11,Assumptions_Config!$C$31:$I$43,3,FALSE),"Other") -> Debt | H11: One-Time | I11: 500000 | J11: 0 | K11: 0.071 | L11: Yes | M11: =IF(L11="Yes",K11,IFERROR(VLOOKUP(C11,Assumptions_Config!$C$31:$I$43,4,FALSE),K11)) -> 0.071 | N11: 0 | O11: Quarterly | P11: =IFERROR(_xludf.SWITCH(O11,"Monthly",12,"Quarterly",4,"Half-Yearly",2,"Annually",1),1) -> 1 | Q11: 5 | R11: Years | S11: =IF(R11="Months",Q11/12,Q11) -> 5 | T11: 5 | U11: =IF(AND(T11<>"",T11>0),T11,S11) -> 5 | W11: =IF(AND(V11<>"",V11>0),V11,Assumptions_Config!$D$9) -> 0.065 | X11: =IFERROR(VLOOKUP(C11,Assumptions_Config!$C$31:$I$43,6,FALSE),5) -> 2 | AA11: Yes | AB11: Tax saver
A12: 4 | B12: Yes | C12: RD | D12: Post Office RD | E12: Self | F12: =IFERROR(VLOOKUP(C12,Assumptions_Config!$C$31:$I$43,2,FALSE),"Other") -> Debt | G12: =IFERROR(VLOOKUP(C12,Assumptions_Config!$C$31:$I$43,3,FALSE),"Other") -> Debt | H12: Recurring | I12: 60000 | J12: 5000 | K12: 0.07 | L12: No | M12: =IF(L12="Yes",K12,IFERROR(VLOOKUP(C12,Assumptions_Config!$C$31:$I$43,4,FALSE),K12)) -> 0.065 | N12: 0 | O12: Quarterly | P12: =IFERROR(_xludf.SWITCH(O12,"Monthly",12,"Quarterly",4,"Half-Yearly",2,"Annually",1),1) -> 1 | Q12: 5 | R12: Years | S12: =IF(R12="Months",Q12/12,Q12) -> 5 | T12: 4 | U12: =IF(AND(T12<>"",T12>0),T12,S12) -> 4 | W12: =IF(AND(V12<>"",V12>0),V12,Assumptions_Config!$D$9) -> 0.065 | X12: =IFERROR(VLOOKUP(C12,Assumptions_Config!$C$31:$I$43,6,FALSE),5) -> 2 | AA12: Yes | AB12: Monthly save
A13: 5 | B13: Yes | C13: PPF | D13: PPF Account | E13: Self | F13: =IFERROR(VLOOKUP(C13,Assumptions_Config!$C$31:$I$43,2,FALSE),"Other") -> Retirement | G13: =IFERROR(VLOOKUP(C13,Assumptions_Config!$C$31:$I$43,3,FALSE),"Other") -> Debt | H13: Recurring | I13: 200000 | J13: 5000 | K13: 0.071 | L13: No | M13: =IF(L13="Yes",K13,IFERROR(VLOOKUP(C13,Assumptions_Config!$C$31:$I$43,4,FALSE),K13)) -> 0.071 | N13: 0 | O13: Annually | P13: =IFERROR(_xludf.SWITCH(O13,"Monthly",12,"Quarterly",4,"Half-Yearly",2,"Annually",1),1) -> 1 | Q13: 15 | R13: Years | S13: =IF(R13="Months",Q13/12,Q13) -> 15 | T13: 12 | U13: =IF(AND(T13<>"",T13>0),T13,S13) -> 12 | W13: =IF(AND(V13<>"",V13>0),V13,Assumptions_Config!$D$9) -> 0.065 | X13: =IFERROR(VLOOKUP(C13,Assumptions_Config!$C$31:$I$43,6,FALSE),5) -> 1 | AA13: No | AB13: Tax-free
A21: 6 | B21: Yes | C21: Gold | D21: Sovereign Gold Bond | E21: Spouse | F21: =IFERROR(VLOOKUP(C21,Assumptions_Config!$C$31:$I$43,2,FALSE),"Other") -> Real Asset | G21: =IFERROR(VLOOKUP(C21,Assumptions_Config!$C$31:$I$43,3,FALSE),"Other") -> Other | H21: One-Time | I21: 300000 | J21: 0 | K21: 0.08 | L21: No | M21: =IF(L21="Yes",K21,IFERROR(VLOOKUP(C21,Assumptions_Config!$C$31:$I$43,4,FALSE),K21)) -> 0.08 | N21: 0 | O21: Annually | P21: =IFERROR(_xludf.SWITCH(O21,"Monthly",12,"Quarterly",4,"Half-Yearly",2,"Annually",1),1) -> 1 | Q21: 8 | R21: Years | S21: =IF(R21="Months",Q21/12,Q21) -> 8 | T21: 6 | U21: =IF(AND(T21<>"",T21>0),T21,S21) -> 6 | W21: =IF(AND(V21<>"",V21>0),V21,Assumptions_Config!$D$9) -> 0.065 | X21: =IFERROR(VLOOKUP(C21,Assumptions_Config!$C$31:$I$43,6,FALSE),5) -> 4 | AA21: Yes | AB21: SGB
A22: 7 | B22: Yes | C22: Stocks | D22: Direct Equity | E22: Self | F22: =IFERROR(VLOOKUP(C22,Assumptions_Config!$C$31:$I$43,2,FALSE),"Other") -> Equity | G22: =IFERROR(VLOOKUP(C22,Assumptions_Config!$C$31:$I$43,3,FALSE),"Other") -> Equity | H22: One-Time | I22: 450000 | J22: 0 | K22: 0.14 | L22: Yes | M22: =IF(L22="Yes",K22,IFERROR(VLOOKUP(C22,Assumptions_Config!$C$31:$I$43,4,FALSE),K22)) -> 0.14 | N22: 0 | O22: Annually | P22: =IFERROR(_xludf.SWITCH(O22,"Monthly",12,"Quarterly",4,"Half-Yearly",2,"Annually",1),1) -> 1 | Q22: 20 | R22: Years | S22: =IF(R22="Months",Q22/12,Q22) -> 20 | T22: 20 | U22: =IF(AND(T22<>"",T22>0),T22,S22) -> 20 | W22: =IF(AND(V22<>"",V22>0),V22,Assumptions_Config!$D$9) -> 0.065 | X22: =IFERROR(VLOOKUP(C22,Assumptions_Config!$C$31:$I$43,6,FALSE),5) -> 8 | AA22: Yes | AB22: LT equity
A23: 8 | B23: Yes | C23: NPS | D23: NPS Tier-1 | E23: Self | F23: =IFERROR(VLOOKUP(C23,Assumptions_Config!$C$31:$I$43,2,FALSE),"Other") -> Retirement | G23: =IFERROR(VLOOKUP(C23,Assumptions_Config!$C$31:$I$43,3,FALSE),"Other") -> Equity | H23: Recurring | I23: 150000 | J23: 4000 | K23: 0.1 | L23: No | M23: =IF(L23="Yes",K23,IFERROR(VLOOKUP(C23,Assumptions_Config!$C$31:$I$43,4,FALSE),K23)) -> 0.1 | N23: 0 | O23: Annually | P23: =IFERROR(_xludf.SWITCH(O23,"Monthly",12,"Quarterly",4,"Half-Yearly",2,"Annually",1),1) -> 1 | Q23: 25 | R23: Years | S23: =IF(R23="Months",Q23/12,Q23) -> 25 | T23: 22 | U23: =IF(AND(T23<>"",T23>0),T23,S23) -> 22 | W23: =IF(AND(V23<>"",V23>0),V23,Assumptions_Config!$D$9) -> 0.065 | X23: =IFERROR(VLOOKUP(C23,Assumptions_Config!$C$31:$I$43,6,FALSE),5) -> 5 | AA23: No | AB23: Retirement
A24: 9 | B24: Yes | C24: Savings Account | D24: HDFC Savings | E24: Self | F24: =IFERROR(VLOOKUP(C24,Assumptions_Config!$C$31:$I$43,2,FALSE),"Other") -> Cash | G24: =IFERROR(VLOOKUP(C24,Assumptions_Config!$C$31:$I$43,3,FALSE),"Other") -> Debt | H24: One-Time | I24: 100000 | J24: 0 | K24: 0.04 | L24: No | M24: =IF(L24="Yes",K24,IFERROR(VLOOKUP(C24,Assumptions_Config!$C$31:$I$43,4,FALSE),K24)) -> 0.04 | N24: 0 | O24: Quarterly | P24: =IFERROR(_xludf.SWITCH(O24,"Monthly",12,"Quarterly",4,"Half-Yearly",2,"Annually",1),1) -> 1 | Q24: 20 | R24: Years | S24: =IF(R24="Months",Q24/12,Q24) -> 20 | T24: 20 | U24: =IF(AND(T24<>"",T24>0),T24,S24) -> 20 | W24: =IF(AND(V24<>"",V24>0),V24,Assumptions_Config!$D$9) -> 0.065 | X24: =IFERROR(VLOOKUP(C24,Assumptions_Config!$C$31:$I$43,6,FALSE),5) -> 1 | AA24: Yes | AB24: Emergency
A25: 10 | B25: Yes | C25: Land | D25: Plot Noida | E25: Self | F25: =IFERROR(VLOOKUP(C25,Assumptions_Config!$C$31:$I$43,2,FALSE),"Other") -> Real Asset | G25: =IFERROR(VLOOKUP(C25,Assumptions_Config!$C$31:$I$43,3,FALSE),"Other") -> Other | H25: One-Time | I25: 2000000 | J25: 0 | K25: 0.1 | L25: No | M25: =IF(L25="Yes",K25,IFERROR(VLOOKUP(C25,Assumptions_Config!$C$31:$I$43,4,FALSE),K25)) -> 0.1 | N25: 0 | O25: Annually | P25: =IFERROR(_xludf.SWITCH(O25,"Monthly",12,"Quarterly",4,"Half-Yearly",2,"Annually",1),1) -> 1 | Q25: 15 | R25: Years | S25: =IF(R25="Months",Q25/12,Q25) -> 15 | T25: 15 | U25: =IF(AND(T25<>"",T25>0),T25,S25) -> 15 | W25: =IF(AND(V25<>"",V25>0),V25,Assumptions_Config!$D$9) -> 0.065 | X25: =IFERROR(VLOOKUP(C25,Assumptions_Config!$C$31:$I$43,6,FALSE),5) -> 6 | AA25: Yes | AB25: Real estate
A26: 11 | B26: Yes | C26: SIP | D26: ELSS Tax Saver SIP | E26: Spouse | F26: =IFERROR(VLOOKUP(C26,Assumptions_Config!$C$31:$I$43,2,FALSE),"Other") -> Equity | G26: =IFERROR(VLOOKUP(C26,Assumptions_Config!$C$31:$I$43,3,FALSE),"Other") -> Equity | H26: Recurring | I26: 50000 | J26: 5000 | K26: 0.13 | L26: No | M26: =IF(L26="Yes",K26,IFERROR(VLOOKUP(C26,Assumptions_Config!$C$31:$I$43,4,FALSE),K26)) -> 0.12 | N26: 0 | O26: Monthly | P26: =IFERROR(_xludf.SWITCH(O26,"Monthly",12,"Quarterly",4,"Half-Yearly",2,"Annually",1),1) -> 1 | Q26: 10 | R26: Years | S26: =IF(R26="Months",Q26/12,Q26) -> 10 | T26: 10 | U26: =IF(AND(T26<>"",T26>0),T26,S26) -> 10 | W26: =IF(AND(V26<>"",V26>0),V26,Assumptions_Config!$D$9) -> 0.065 | X26: =IFERROR(VLOOKUP(C26,Assumptions_Config!$C$31:$I$43,6,FALSE),5) -> 7 | AA26: No | AB26: 80C benefit
A27: 12 | B27: Yes | C27: Crypto | D27: Bitcoin + ETH | E27: Self | F27: =IFERROR(VLOOKUP(C27,Assumptions_Config!$C$31:$I$43,2,FALSE),"Other") -> Alternative | G27: =IFERROR(VLOOKUP(C27,Assumptions_Config!$C$31:$I$43,3,FALSE),"Other") -> Other | H27: One-Time | I27: 100000 | J27: 0 | K27: 0.15 | L27: No | M27: =IF(L27="Yes",K27,IFERROR(VLOOKUP(C27,Assumptions_Config!$C$31:$I$43,4,FALSE),K27)) -> 0.15 | N27: 0 | O27: Annually | P27: =IFERROR(_xludf.SWITCH(O27,"Monthly",12,"Quarterly",4,"Half-Yearly",2,"Annually",1),1) -> 1 | Q27: 10 | R27: Years | S27: =IF(R27="Months",Q27/12,Q27) -> 10 | T27: 10 | U27: =IF(AND(T27<>"",T27>0),T27,S27) -> 10 | W27: =IF(AND(V27<>"",V27>0),V27,Assumptions_Config!$D$9) -> 0.065 | X27: =IFERROR(VLOOKUP(C27,Assumptions_Config!$C$31:$I$43,6,FALSE),5) -> 10 | AA27: Yes | AB27: High risk

Sheet Debt_Tracker
A1: DEBT & LIABILITY TRACKER
A2: TRUE Net Worth = Assets − Liabilities | Enter all loans below
A4: ID | B4: Loan Type | C4: Lender | D4: Outstanding ₹ | E4: EMI ₹ | F4: Interest % | G4: Remaining Months | H4: Total Remaining | I4: Interest Cost | J4: Priority | K4: Notes
A5: 1 | B5: Home Loan | C5: SBI | D5: 3500000 | E5: 32000 | F5: 0.085 | G5: 180 | H5: =E5*G5 -> 5760000 | I5: =H5-D5 -> 2260000 | J5: =IF(F5>=0.15,"🔴 HIGH",IF(F5>=0.1,"🟡 MED","🟢 LOW")) -> 🟢 LOW
A6: 2 | B6: Car Loan | C6: HDFC | D6: 450000 | E6: 12000 | F6: 0.092 | G6: 42 | H6: =E6*G6 -> 504000 | I6: =H6-D6 -> 54000 | J6: =IF(F6>=0.15,"🔴 HIGH",IF(F6>=0.1,"🟡 MED","🟢 LOW")) -> 🟢 LOW
A7: 3 | B7: Personal Loan | C7: Bajaj | D7: 200000 | E7: 8000 | F7: 0.14 | G7: 28 | H7: =E7*G7 -> 224000 | I7: =H7-D7 -> 24000 | J7: =IF(F7>=0.15,"🔴 HIGH",IF(F7>=0.1,"🟡 MED","🟢 LOW")) -> 🟡 MED
A8: 4 | B8: Credit Card | C8: ICICI | D8: 85000 | E8: 5000 | F8: 0.36 | G8: 0 | H8: =E8*G8 -> 0 | I8: =H8-D8 -> -85000 | J8: =IF(F8>=0.15,"🔴 HIGH",IF(F8>=0.1,"🟡 MED","🟢 LOW")) -> 🔴 HIGH
A10: DEBT SUMMARY
A11: Total Outstanding | C11: =SUM(D5:D8) -> 4235000
A12: Total Monthly EMI | C12: =SUM(E5:E8) -> 57000
A13: Total Interest Cost | C13: =SUM(I5:I8) -> 2253000
A14: Debt-to-Asset Ratio | C14: =IF(Investment_Input!C4=0,0,SUM(D5:D8)/Investment_Input!C4) -> 1.0291616
A15: Debt-to-Income Ratio | C15: =IF(Assumptions_Config!$D$17=0,0,SUM(D5:D8)/Assumptions_Config!$D$17) -> 2.3527778

Sheet Income_Expenses
A1: INCOME & EXPENSE TRACKER
A2: Track cash flow | Calculates savings rate & investable surplus
A4: MONTHLY INCOME
A5: Source | B5: Amount (₹/month) | C5: Type | D5: Notes
A6: Salary | B6: 120000 | C6: Active | D6: Post-tax take-home
A7: Rental Income | B7: 15000 | C7: Passive | D7: Property rental
A8: Freelance/Side Income | B8: 20000 | C8: Variable | D8: Consulting
A9: Dividend/Interest | B9: 3000 | C9: Passive | D9: Portfolio income
A11: TOTAL MONTHLY INCOME | B11: =SUM(B6:B9) -> 158000
A13: MONTHLY EXPENSES
A14: Category | B14: Amount (₹/month) | C14: Essential? | D14: Notes
A15: Rent/Home EMI | B15: 32000 | C15: Yes | D15: Housing
A16: Groceries & Food | B16: 15000 | C16: Yes | D16: Monthly groceries
A17: Utilities | B17: 5000 | C17: Yes | D17: Electric, water, gas, internet
A18: Insurance Premiums | B18: 4000 | C18: Yes | D18: Life + health + vehicle
A19: Children Education | B19: 12000 | C19: Yes | D19: School fees
A20: Transport/Fuel | B20: 6000 | C20: Semi | D20: Car fuel, maintenance
A21: Lifestyle/Entertainment | B21: 15000 | C21: No | D21: Dining, shopping, OTT
A22: Miscellaneous | B22: 5000 | C22: No | D22: Buffer expenses
A24: TOTAL MONTHLY EXPENSES | B24: =SUM(B15:B22) -> 94000
A26: CASH FLOW SUMMARY
A28: Total Income | B28: =B11 -> 158000
A29: Total Expenses | B29: =B24 -> 94000
A30: Total EMIs (Loans) | B30: =Debt_Tracker!C12 -> 57000
A31: Current SIPs/Investments | B31: =Investment_Input!C5 -> 27000
A32: NET SURPLUS / DEFICIT | B32: =B28-B29-B30-B31 -> -20000
A33: Savings Rate % | B33: =IF(B28=0,0,(B28-B29)/B28) -> 0.40506329
A34: Investment Rate % | B34: =IF(B28=0,0,B31/B28) -> 0.17088608
A35: Uninvested Surplus | B35: =B32 -> -20000

Sheet Major_Expenses
A1: MAJOR FUTURE EXPENSES
A2: Reduce projected wealth | Enter in today's or future value
A4: ID | B4: Name | C4: Category | D4: Year | E4: Amount | F4: Amt Type | G4: Inflate? | H4: Inf Rate | I4: Yrs Until | J4: Future Value | K4: Notes
A5: 1 | B5: Child's Wedding | C5: Wedding | D5: 2035 | E5: 3000000 | F5: Today's Value | G5: Yes | H5: =IF(G5="Yes",Assumptions_Config!$D$5,0) -> 0.1 | I5: =MAX(D5-2026,0) -> 9 | J5: =IF(F5="Future Value",E5,IF(G5="Yes",E5*(1+Assumptions_Config!$D$5)^I5,E5)) -> 7073843.1
A6: 2 | B6: House Down Payment | C6: House | D6: 2028 | E6: 2500000 | F6: Today's Value | G6: Yes | H6: =IF(G6="Yes",Assumptions_Config!$D$5,0) -> 0.1 | I6: =MAX(D6-2026,0) -> 2 | J6: =IF(F6="Future Value",E6,IF(G6="Yes",E6*(1+Assumptions_Config!$D$5)^I6,E6)) -> 3025000
A7: 3 | B7: Car Upgrade | C7: Car | D7: 2030 | E7: 1500000 | F7: Future Value | G7: No | H7: =IF(G7="Yes",Assumptions_Config!$D$5,0) -> 0 | I7: =MAX(D7-2026,0) -> 4 | J7: =IF(F7="Future Value",E7,IF(G7="Yes",E7*(1+Assumptions_Config!$D$5)^I7,E7)) -> 1500000
A8: 4 | B8: Higher Education | C8: Education | D8: 2032 | E8: 2000000 | F8: Today's Value | G8: Yes | H8: =IF(G8="Yes",Assumptions_Config!$D$5,0) -> 0.1 | I8: =MAX(D8-2026,0) -> 6 | J8: =IF(F8="Future Value",E8,IF(G8="Yes",E8*(1+Assumptions_Config!$D$5)^I8,E8)) -> 3543122
A9: 5 | B9: Medical Reserve | C9: Medical | D9: 2027 | E9: 500000 | F9: Today's Value | G9: Yes | H9: =IF(G9="Yes",Assumptions_Config!$D$5,0) -> 0.1 | I9: =MAX(D9-2026,0) -> 1 | J9: =IF(F9="Future Value",E9,IF(G9="Yes",E9*(1+Assumptions_Config!$D$5)^I9,E9)) -> 550000

Sheet Goals_Tracker
A1: GOAL-BASED WEALTH PLANNING
A2: Link investments to goals | Track funding status
A4: Goal | B4: Target ₹ | C4: Target Year | D4: Current Funded ₹ | E4: Monthly Allocation | F4: Years Left | G4: FV of Goal | H4: Projected Funded | I4: Shortfall | J4: Funded % | K4: Status
A5: Retirement Corpus | B5: 50000000 | C5: 2050 | D5: 350000 | E5: 17000 | F5: =MAX(C5-2026,0) -> 24 | G5: =B5*(1+Assumptions_Config!$D$5)^F5 -> 4.9248663e+08 | H5: =D5*(1+Assumptions_Config!$D$63)^F5+IF(F5>0,E5*((1+Assumptions_Config!$D$63/12)^(F5*12)-1)/(Assumptions_Config!$D$63/12),0) -> 23672163 | I5: =G5-H5 -> 4.6881447e+08 | J5: =IF(G5=0,0,MIN(H5/G5,1)) -> 0.048066611 | K5: =IF(J5>=0.9,"🟢 On Track",IF(J5>=0.6,"🟡 At Risk","🔴 Behind")) -> 🔴 Behind
A6: Child's Education | B6: 5000000 | C6: 2035 | D6: 200000 | E6: 5000 | F6: =MAX(C6-2026,0) -> 9 | G6: =B6*(1+Assumptions_Config!$D$5)^F6 -> 11789738 | H6: =D6*(1+Assumptions_Config!$D$63)^F6+IF(F6>0,E6*((1+Assumptions_Config!$D$63/12)^(F6*12)-1)/(Assumptions_Config!$D$63/12),0) -> 1341858.1 | I6: =G6-H6 -> 10447880 | J6: =IF(G6=0,0,MIN(H6/G6,1)) -> 0.11381577 | K6: =IF(J6>=0.9,"🟢 On Track",IF(J6>=0.6,"🟡 At Risk","🔴 Behind")) -> 🔴 Behind
A7: House Purchase | B7: 15000000 | C7: 2030 | D7: 2500000 | E7: 10000 | F7: =MAX(C7-2026,0) -> 4 | G7: =B7*(1+Assumptions_Config!$D$5)^F7 -> 21961500 | H7: =D7*(1+Assumptions_Config!$D$63)^F7+IF(F7>0,E7*((1+Assumptions_Config!$D$63/12)^(F7*12)-1)/(Assumptions_Config!$D$63/12),0) -> 4247474.9 | I7: =G7-H7 -> 17714025 | J7: =IF(G7=0,0,MIN(H7/G7,1)) -> 0.1934055 | K7: =IF(J7>=0.9,"🟢 On Track",IF(J7>=0.6,"🟡 At Risk","🔴 Behind")) -> 🔴 Behind
A8: Emergency Fund | B8: 480000 | C8: 2027 | D8: 100000 | E8: 8000 | F8: =MAX(C8-2026,0) -> 1 | G8: =B8*(1+Assumptions_Config!$D$5)^F8 -> 528000 | H8: =D8*(1+Assumptions_Config!$D$63)^F8+IF(F8>0,E8*((1+Assumptions_Config!$D$63/12)^(F8*12)-1)/(Assumptions_Config!$D$63/12),0) -> 210524.54 | I8: =G8-H8 -> 317475.46 | J8: =IF(G8=0,0,MIN(H8/G8,1)) -> 0.39872073 | K8: =IF(J8>=0.9,"🟢 On Track",IF(J8>=0.6,"🟡 At Risk","🔴 Behind")) -> 🔴 Behind
A9: Vacation Fund | B9: 500000 | C9: 2027 | D9: 50000 | E9: 3000 | F9: =MAX(C9-2026,0) -> 1 | G9: =B9*(1+Assumptions_Config!$D$5)^F9 -> 550000 | H9: =D9*(1+Assumptions_Config!$D$63)^F9+IF(F9>0,E9*((1+Assumptions_Config!$D$63/12)^(F9*12)-1)/(Assumptions_Config!$D$63/12),0) -> 92696.704 | I9: =G9-H9 -> 457303.3 | J9: =IF(G9=0,0,MIN(H9/G9,1)) -> 0.16853946 | K9: =IF(J9>=0.9,"🟢 On Track",IF(J9>=0.6,"🟡 At Risk","🔴 Behind")) -> 🔴 Behind

Sheet Insurance_Summary
A1: INSURANCE GAP ANALYSIS
A2: Life + Health + Vehicle coverage adequacy check
A4: Type | B4: Provider | C4: Sum Assured ₹ | D4: Premium/Year ₹ | E4: Expiry | F4: Cover Type | G4: Notes
A5: Term Life | B5: HDFC Life | C5: 10000000 | D5: 12000 | E5: 2045 | F5: Individual | G5: Pure term
A6: Health | B6: Star Health | C6: 1000000 | D6: 18000 | E6: 2027 | F6: Family | G6: Family floater
A7: Critical Illness | B7: ICICI Pru | C7: 2500000 | D7: 8000 | E7: 2040 | F7: Individual | G7: CI rider
A8: Vehicle | B8: ICICI Lombard | C8: 800000 | D8: 9000 | E8: 2027 | F8: Comprehensive
A10: INSURANCE GAP ANALYSIS
A12: Annual Income | B12: =Assumptions_Config!$D$17 -> 1800000
A13: Life Cover Needed (10× income) | B13: =Assumptions_Config!$D$17*10 -> 18000000
A14: Current Life Cover | B14: =SUMPRODUCT((A5:A8="Term Life")*C5:C8) -> 10000000
A15: LIFE COVER GAP | B15: =B13-B14 -> 8000000
A16: Health Cover Needed (₹) | B16: 1000000
A17: Current Health Cover | B17: =SUMPRODUCT((A5:A8="Health")*C5:C8) -> 1000000
A18: HEALTH COVER GAP | B18: =B16-B17 -> 0
A19: Total Annual Premiums | B19: =SUM(D5:D8) -> 47000
A20: Premium as % of Income | B20: =IF(Assumptions_Config!$D$17=0,0,B19/Assumptions_Config!$D$17) -> 0.026111111

Sheet Helper_Calcs
A1: HELPER CALCULATIONS — DO NOT EDIT
A2: All intermediate calculations | Can be hidden
A4: A. INDIVIDUAL PROJECTIONS
A5: ID | B5: Active | C5: Type | D5: Bucket | E5: Cur Val | F5: Monthly | G5: Eff Ret | H5: StepUp | I5: Eff Tenure | J5: Tax? | K5: Horizon | L5: FV Lump | M5: FV Recur | N5: Total@Mat | O5: Val@Horizon | P5: Contributions | Q5: Gains | R5: Tax | S5: Post-Tax | T5: Inf-Adj
A6: =Investment_Input!A9 -> 1 | B6: =Investment_Input!B9 -> Yes | C6: =Investment_Input!C9 -> SIP | D6: =Investment_Input!G9 -> Equity | E6: =Investment_Input!I9 -> 125000 | F6: =Investment_Input!J9 -> 5000 | G6: =Investment_Input!M9 -> 0.12 | H6: =Investment_Input!N9 -> 0.1 | I6: =Investment_Input!U9 -> 15 | J6: =Investment_Input!AA9 -> Yes | K6: =Assumptions_Config!$D$8 -> 15 | L6: =IF(B6<>"Yes",0,E6*(1+G6)^MIN(I6,K6)) -> 684195.72 | M6: =IF(OR(F6=0,B6<>"Yes"),0,IF(G6=0,F6*MIN(I6,K6)*12,F6*((1+G6/12)^(MIN(I6,K6)*12)-1)/(G6/12)*(1+G6/12)*(1+H6/2))) -> 2649024 | N6: =L6+M6 -> 3333219.7 | O6: =IF(K6>I6,N6*(1+Assumptions_Config!$D$9)^(K6-I6),N6) -> 3333219.7 | P6: =E6+IF(F6=0,0,F6*MIN(I6,K6)*12*(1+H6/2)) -> 1070000 | Q6: =MAX(O6-P6,0) -> 2263219.7 | R6: =IF(J6="Yes",Q6*Assumptions_Config!$D$6,0) -> 565804.93 | S6: =O6-R6 -> 2767414.8 | T6: =S6/(1+Assumptions_Config!$D$5)^Assumptions_Config!$D$8 -> 662497.1
A7: =Investment_Input!A10 -> 2 | B7: =Investment_Input!B10 -> Yes | C7: =Investment_Input!C10 -> SIP | D7: =Investment_Input!G10 -> Equity | E7: =Investment_Input!I10 -> 80000 | F7: =Investment_Input!J10 -> 3000 | G7: =Investment_Input!M10 -> 0.14 | H7: =Investment_Input!N10 -> 0.05 | I7: =Investment_Input!U10 -> 10 | J7: =Investment_Input!AA10 -> Yes | K7: =Assumptions_Config!$D$8 -> 15 | L7: =IF(B7<>"Yes",0,E7*(1+G7)^MIN(I7,K7)) -> 296577.71 | M7: =IF(OR(F7=0,B7<>"Yes"),0,IF(G7=0,F7*MIN(I7,K7)*12,F7*((1+G7/12)^(MIN(I7,K7)*12)-1)/(G7/12)*(1+G7/12)*(1+H7/2))) -> 805931 | N7: =L7+M7 -> 1102508.7 | O7: =IF(K7>I7,N7*(1+Assumptions_Config!$D$9)^(K7-I7),N7) -> 1510532.5 | P7: =E7+IF(F7=0,0,F7*MIN(I7,K7)*12*(1+H7/2)) -> 449000 | Q7: =MAX(O7-P7,0) -> 1061532.5 | R7: =IF(J7="Yes",Q7*Assumptions_Config!$D$6,0) -> 265383.12 | S7: =O7-R7 -> 1245149.4 | T7: =S7/(1+Assumptions_Config!$D$5)^Assumptions_Config!$D$8 -> 298078.86
A8: =Investment_Input!A11 -> 3 | B8: =Investment_Input!B11 -> Yes | C8: =Investment_Input!C11 -> FD | D8: =Investment_Input!G11 -> Debt | E8: =Investment_Input!I11 -> 500000 | F8: =Investment_Input!J11 -> 0 | G8: =Investment_Input!M11 -> 0.071 | H8: =Investment_Input!N11 -> 0 | I8: =Investment_Input!U11 -> 5 | J8: =Investment_Input!AA11 -> Yes | K8: =Assumptions_Config!$D$8 -> 15 | L8: =IF(B8<>"Yes",0,E8*(1+G8)^MIN(I8,K8)) -> 704558.99 | M8: =IF(OR(F8=0,B8<>"Yes"),0,IF(G8=0,F8*MIN(I8,K8)*12,F8*((1+G8/12)^(MIN(I8,K8)*12)-1)/(G8/12)*(1+G8/12)*(1+H8/2))) -> 0 | N8: =L8+M8 -> 704558.99 | O8: =IF(K8>I8,N8*(1+Assumptions_Config!$D$9)^(K8-I8),N8) -> 1322554.1 | P8: =E8+IF(F8=0,0,F8*MIN(I8,K8)*12*(1+H8/2)) -> 500000 | Q8: =MAX(O8-P8,0) -> 822554.07 | R8: =IF(J8="Yes",Q8*Assumptions_Config!$D$6,0) -> 205638.52 | S8: =O8-R8 -> 1116915.6 | T8: =S8/(1+Assumptions_Config!$D$5)^Assumptions_Config!$D$8 -> 267380.7
A9: =Investment_Input!A12 -> 4 | B9: =Investment_Input!B12 -> Yes | C9: =Investment_Input!C12 -> RD | D9: =Investment_Input!G12 -> Debt | E9: =Investment_Input!I12 -> 60000 | F9: =Investment_Input!J12 -> 5000 | G9: =Investment_Input!M12 -> 0.065 | H9: =Investment_Input!N12 -> 0 | I9: =Investment_Input!U12 -> 4 | J9: =Investment_Input!AA12 -> Yes | K9: =Assumptions_Config!$D$8 -> 15 | L9: =IF(B9<>"Yes",0,E9*(1+G9)^MIN(I9,K9)) -> 77187.981 | M9: =IF(OR(F9=0,B9<>"Yes"),0,IF(G9=0,F9*MIN(I9,K9)*12,F9*((1+G9/12)^(MIN(I9,K9)*12)-1)/(G9/12)*(1+G9/12)*(1+H9/2))) -> 274729.73 | N9: =L9+M9 -> 351917.72 | O9: =IF(K9>I9,N9*(1+Assumptions_Config!$D$9)^(K9-I9),N9) -> 703536.79 | P9: =E9+IF(F9=0,0,F9*MIN(I9,K9)*12*(1+H9/2)) -> 300000 | Q9: =MAX(O9-P9,0) -> 403536.79 | R9: =IF(J9="Yes",Q9*Assumptions_Config!$D$6,0) -> 100884.2 | S9: =O9-R9 -> 602652.6 | T9: =S9/(1+Assumptions_Config!$D$5)^Assumptions_Config!$D$8 -> 144270.24
A10: =Investment_Input!A13 -> 5 | B10: =Investment_Input!B13 -> Yes | C10: =Investment_Input!C13 -> PPF | D10: =Investment_Input!G13 -> Debt | E10: =Investment_Input!I13 -> 200000 | F10: =Investment_Input!J13 -> 5000 | G10: =Investment_Input!M13 -> 0.071 | H10: =Investment_Input!N13 -> 0 | I10: =Investment_Input!U13 -> 12 | J10: =Investment_Input!AA13 -> No | K10: =Assumptions_Config!$D$8 -> 15 | L10: =IF(B10<>"Yes",0,E10*(1+G10)^MIN(I10,K10)) -> 455516.01 | M10: =IF(OR(F10=0,B10<>"Yes"),0,IF(G10=0,F10*MIN(I10,K10)*12,F10*((1+G10/12)^(MIN(I10,K10)*12)-1)/(G10/12)*(1+G10/12)*(1+H10/2))) -> 1137778.9 | N10: =L10+M10 -> 1593294.9 | O10: =IF(K10>I10,N10*(1+Assumptions_Config!$D$9)^(K10-I10),N10) -> 1924620 | P10: =E10+IF(F10=0,0,F10*MIN(I10,K10)*12*(1+H10/2)) -> 920000 | Q10: =MAX(O10-P10,0) -> 1004620 | R10: =IF(J10="Yes",Q10*Assumptions_Config!$D$6,0) -> 0 | S10: =O10-R10 -> 1924620 | T10: =S10/(1+Assumptions_Config!$D$5)^Assumptions_Config!$D$8 -> 460738.73
A11: =Investment_Input!A21 -> 6 | B11: =Investment_Input!B21 -> Yes | C11: =Investment_Input!C21 -> Gold | D11: =Investment_Input!G21 -> Other | E11: =Investment_Input!I21 -> 300000 | F11: =Investment_Input!J21 -> 0 | G11: =Investment_Input!M21 -> 0.08 | H11: =Investment_Input!N21 -> 0 | I11: =Investment_Input!U21 -> 6 | J11: =Investment_Input!AA21 -> Yes | K11: =Assumptions_Config!$D$8 -> 15 | L11: =IF(B11<>"Yes",0,E11*(1+G11)^MIN(I11,K11)) -> 476062.3 | M11: =IF(OR(F11=0,B11<>"Yes"),0,IF(G11=0,F11*MIN(I11,K11)*12,F11*((1+G11/12)^(MIN(I11,K11)*12)-1)/(G11/12)*(1+G11/12)*(1+H11/2))) -> 0 | N11: =L11+M11 -> 476062.3 | O11: =IF(K11>I11,N11*(1+Assumptions_Config!$D$9)^(K11-I11),N11) -> 839093.31 | P11: =E11+IF(F11=0,0,F11*MIN(I11,K11)*12*(1+H11/2)) -> 300000 | Q11: =MAX(O11-P11,0) -> 539093.31 | R11: =IF(J11="Yes",Q11*Assumptions_Config!$D$6,0) -> 134773.33 | S11: =O11-R11 -> 704319.98 | T11: =S11/(1+Assumptions_Config!$D$5)^Assumptions_Config!$D$8 -> 168608.6
A12: =Investment_Input!A22 -> 7 | B12: =Investment_Input!B22 -> Yes | C12: =Investment_Input!C22 -> Stocks | D12: =Investment_Input!G22 -> Equity | E12: =Investment_Input!I22 -> 450000 | F12: =Investment_Input!J22 -> 0 | G12: =Investment_Input!M22 -> 0.14 | H12: =Investment_Input!N22 -> 0 | I12: =Investment_Input!U22 -> 20 | J12: =Investment_Input!AA22 -> Yes | K12: =Assumptions_Config!$D$8 -> 15 | L12: =IF(B12<>"Yes",0,E12*(1+G12)^MIN(I12,K12)) -> 3212072.1 | M12: =IF(OR(F12=0,B12<>"Yes"),0,IF(G12=0,F12*MIN(I12,K12)*12,F12*((1+G12/12)^(MIN(I12,K12)*12)-1)/(G12/12)*(1+G12/12)*(1+H12/2))) -> 0 | N12: =L12+M12 -> 3212072.1 | O12: =IF(K12>I12,N12*(1+Assumptions_Config!$D$9)^(K12-I12),N12) -> 3212072.1 | P12: =E12+IF(F12=0,0,F12*MIN(I12,K12)*12*(1+H12/2)) -> 450000 | Q12: =MAX(O12-P12,0) -> 2762072.1 | R12: =IF(J12="Yes",Q12*Assumptions_Config!$D$6,0) -> 690518.02 | S12: =O12-R12 -> 2521554.1 | T12: =S12/(1+Assumptions_Config!$D$5)^Assumptions_Config!$D$8 -> 603640
A13: =Investment_Input!A23 -> 8 | B13: =Investment_Input!B23 -> Yes | C13: =Investment_Input!C23 -> NPS | D13: =Investment_Input!G23 -> Equity | E13: =Investment_Input!I23 -> 150000 | F13: =Investment_Input!J23 -> 4000 | G13: =Investment_Input!M23 -> 0.1 | H13: =Investment_Input!N23 -> 0 | I13: =Investment_Input!U23 -> 22 | J13: =Investment_Input!AA23 -> No | K13: =Assumptions_Config!$D$8 -> 15 | L13: =IF(B13<>"Yes",0,E13*(1+G13)^MIN(I13,K13)) -> 626587.23 | M13: =IF(OR(F13=0,B13<>"Yes"),0,IF(G13=0,F13*MIN(I13,K13)*12,F13*((1+G13/12)^(MIN(I13,K13)*12)-1)/(G13/12)*(1+G13/12)*(1+H13/2))) -> 1671697.1 | N13: =L13+M13 -> 2298284.3 | O13: =IF(K13>I13,N13*(1+Assumptions_Config!$D$9)^(K13-I13),N13) -> 2298284.3 | P13: =E13+IF(F13=0,0,F13*MIN(I13,K13)*12*(1+H13/2)) -> 870000 | Q13: =MAX(O13-P13,0) -> 1428284.3 | R13: =IF(J13="Yes",Q13*Assumptions_Config!$D$6,0) -> 0 | S13: =O13-R13 -> 2298284.3 | T13: =S13/(1+Assumptions_Config!$D$5)^Assumptions_Config!$D$8 -> 550190.99
A14: =Investment_Input!A24 -> 9 | B14: =Investment_Input!B24 -> Yes | C14: =Investment_Input!C24 -> Savings Account | D14: =Investment_Input!G24 -> Debt | E14: =Investment_Input!I24 -> 100000 | F14: =Investment_Input!J24 -> 0 | G14: =Investment_Input!M24 -> 0.04 | H14: =Investment_Input!N24 -> 0 | I14: =Investment_Input!U24 -> 20 | J14: =Investment_Input!AA24 -> Yes | K14: =Assumptions_Config!$D$8 -> 15 | L14: =IF(B14<>"Yes",0,E14*(1+G14)^MIN(I14,K14)) -> 180094.35 | M14: =IF(OR(F14=0,B14<>"Yes"),0,IF(G14=0,F14*MIN(I14,K14)*12,F14*((1+G14/12)^(MIN(I14,K14)*12)-1)/(G14/12)*(1+G14/12)*(1+H14/2))) -> 0 | N14: =L14+M14 -> 180094.35 | O14: =IF(K14>I14,N14*(1+Assumptions_Config!$D$9)^(K14-I14),N14) -> 180094.35 | P14: =E14+IF(F14=0,0,F14*MIN(I14,K14)*12*(1+H14/2)) -> 100000 | Q14: =MAX(O14-P14,0) -> 80094.351 | R14: =IF(J14="Yes",Q14*Assumptions_Config!$D$6,0) -> 20023.588 | S14: =O14-R14 -> 160070.76 | T14: =S14/(1+Assumptions_Config!$D$5)^Assumptions_Config!$D$8 -> 38319.668
A15: =Investment_Input!A25 -> 10 | B15: =Investment_Input!B25 -> Yes | C15: =Investment_Input!C25 -> Land | D15: =Investment_Input!G25 -> Other | E15: =Investment_Input!I25 -> 2000000 | F15: =Investment_Input!J25 -> 0 | G15: =Investment_Input!M25 -> 0.1 | H15: =Investment_Input!N25 -> 0 | I15: =Investment_Input!U25 -> 15 | J15: =Investment_Input!AA25 -> Yes | K15: =Assumptions_Config!$D$8 -> 15 | L15: =IF(B15<>"Yes",0,E15*(1+G15)^MIN(I15,K15)) -> 8354496.3 | M15: =IF(OR(F15=0,B15<>"Yes"),0,IF(G15=0,F15*MIN(I15,K15)*12,F15*((1+G15/12)^(MIN(I15,K15)*12)-1)/(G15/12)*(1+G15/12)*(1+H15/2))) -> 0 | N15: =L15+M15 -> 8354496.3 | O15: =IF(K15>I15,N15*(1+Assumptions_Config!$D$9)^(K15-I15),N15) -> 8354496.3 | P15: =E15+IF(F15=0,0,F15*MIN(I15,K15)*12*(1+H15/2)) -> 2000000 | Q15: =MAX(O15-P15,0) -> 6354496.3 | R15: =IF(J15="Yes",Q15*Assumptions_Config!$D$6,0) -> 1588624.1 | S15: =O15-R15 -> 6765872.3 | T15: =S15/(1+Assumptions_Config!$D$5)^Assumptions_Config!$D$8 -> 1619696
A16: =Investment_Input!A26 -> 11 | B16: =Investment_Input!B26 -> Yes | C16: =Investment_Input!C26 -> SIP | D16: =Investment_Input!G26 -> Equity | E16: =Investment_Input!I26 -> 50000 | F16: =Investment_Input!J26 -> 5000 | G16: =Investment_Input!M26 -> 0.12 | H16: =Investment_Input!N26 -> 0 | I16: =Investment_Input!U26 -> 10 | J16: =Investment_Input!AA26 -> No | K16: =Assumptions_Config!$D$8 -> 15 | L16: =IF(B16<>"Yes",0,E16*(1+G16)^MIN(I16,K16)) -> 155292.41 | M16: =IF(OR(F16=0,B16<>"Yes"),0,IF(G16=0,F16*MIN(I16,K16)*12,F16*((1+G16/12)^(MIN(I16,K16)*12)-1)/(G16/12)*(1+G16/12)*(1+H16/2))) -> 1161695.4 | N16: =L16+M16 -> 1316987.8 | O16: =IF(K16>I16,N16*(1+Assumptions_Config!$D$9)^(K16-I16),N16) -> 1804387.4 | P16: =E16+IF(F16=0,0,F16*MIN(I16,K16)*12*(1+H16/2)) -> 650000 | Q16: =MAX(O16-P16,0) -> 1154387.4 | R16: =IF(J16="Yes",Q16*Assumptions_Config!$D$6,0) -> 0 | S16: =O16-R16 -> 1804387.4 | T16: =S16/(1+Assumptions_Config!$D$5)^Assumptions_Config!$D$8 -> 431956
A17: =Investment_Input!A27 -> 12 | B17: =Investment_Input!B27 -> Yes | C17: =Investment_Input!C27 -> Crypto | D17: =Investment_Input!G27 -> Other | E17: =Investment_Input!I27 -> 100000 | F17: =Investment_Input!J27 -> 0 | G17: =Investment_Input!M27 -> 0.15 | H17: =Investment_Input!N27 -> 0 | I17: =Investment_Input!U27 -> 10 | J17: =Investment_Input!AA27 -> Yes | K17: =Assumptions_Config!$D$8 -> 15 | L17: =IF(B17<>"Yes",0,E17*(1+G17)^MIN(I17,K17)) -> 404555.77 | M17: =IF(OR(F17=0,B17<>"Yes"),0,IF(G17=0,F17*MIN(I17,K17)*12,F17*((1+G17/12)^(MIN(I17,K17)*12)-1)/(G17/12)*(1+G17/12)*(1+H17/2))) -> 0 | N17: =L17+M17 -> 404555.77 | O17: =IF(K17>I17,N17*(1+Assumptions_Config!$D$9)^(K17-I17),N17) -> 554276.47 | P17: =E17+IF(F17=0,0,F17*MIN(I17,K17)*12*(1+H17/2)) -> 100000 | Q17: =MAX(O17-P17,0) -> 454276.47 | R17: =IF(J17="Yes",Q17*Assumptions_Config!$D$6,0) -> 113569.12 | S17: =O17-R17 -> 440707.35 | T17: =S17/(1+Assumptions_Config!$D$5)^Assumptions_Config!$D$8 -> 105501.84
A20: B. PORTFOLIO AGGREGATION
A21: Current Asset Value | B21: =SUMPRODUCT((B6:B17="Yes")*E6:E17) -> 4115000
A22: Projected Nominal | B22: =SUMPRODUCT((B6:B17="Yes")*O6:O17) -> 26037167
A23: Post-Tax NW | B23: =SUMPRODUCT((B6:B17="Yes")*S6:S17) -> 22351948
A24: Tax Deducted | B24: =SUMPRODUCT((B6:B17="Yes")*R6:R17) -> 3685218.9
A25: Contributions | B25: =SUMPRODUCT((B6:B17="Yes")*P6:P17) -> 7709000
A26: Gains | B26: =B22-B25 -> 18328167
A27: Inflation-Adj | B27: =B23/(1+Assumptions_Config!$D$5)^Assumptions_Config!$D$8 -> 5350878.7
A28: Future Expenses | B28: =SUM(Major_Expenses!J5:J9) -> 15691965
A29: Total Debt | B29: =Debt_Tracker!C11 -> 4235000
A30: TRUE Net Worth (Pre-Tax) | B30: =B21-B29 -> -120000
A31: TRUE Net Worth (Post-Tax) | B31: =B23-B29 -> 18116948
A32: Net After Expenses | B32: =B31-B28 -> 2424983.3
A33: Inflation Erosion ₹ | B33: =B23-B27 -> 17001070
A34: Inflation Erosion % | B34: =IF(B23<>0,B33/B23,0) -> 0.76060795
A35: Monthly Investment | B35: =SUMPRODUCT((Investment_Input!B9:B28="Yes")*(Investment_Input!H9:H28="Recurring")*Investment_Input!J9:J28) -> 27000
A36: Emergency Fund Needed | B36: =Assumptions_Config!$D$12*Assumptions_Config!$D$13 -> 600000
A37: Liquid Assets | B37: =SUMPRODUCT((Investment_Input!B9:B28="Yes")*(Investment_Input!C9:C28="Savings Account")*Investment_Input!I9:I28)+SUMPRODUCT((Investment_Input!B9:B28="Yes")*(Investment_Input!C9:C28="FD")*Investment_Input!I9:I28) -> 600000
A38: Emergency Ratio | B38: =IF(B36=0,0,B37/B36) -> 1
A39: Wtd Risk Score | B39: =Investment_Input!J4 -> 5.2867558
A40: Portfolio Risk Level | B40: =IF(B39>=8,"Very Aggressive",IF(B39>=6,"Aggressive",IF(B39>=3,"Moderate","Conservative"))) -> Moderate
A41: Display Factor | B41: =_xludf.SWITCH(Assumptions_Config!$D$7,"₹",1,"Lakhs",100000,"Crores",10000000,"Millions",1000000,1) -> #NAME?
A42: Display Unit | B42: =Assumptions_Config!$D$7 -> Lakhs
A43: C. ALLOCATION & REBALANCING
A44: Bucket | B44: Current Val | C44: Post-Tax | D44: Cur% | E44: Target% | F44: Deviation | G44: Action
A45: Equity | B45: =SUMPRODUCT((B6:B17="Yes")*(D6:D17="Equity")*E6:E17) -> 855000 | C45: =SUMPRODUCT((B6:B17="Yes")*(D6:D17="Equity")*S6:S17) -> 10636790 | D45: =IF(B21<>0,B45/B21,0) -> 0.20777643 | E45: =Assumptions_Config!D57 -> 0.7 | F45: =D45-E45 -> -0.49222357 | G45: =IF(ABS(F45)<0.02,"✅ On target",IF(F45>0,"↓ Reduce by ₹"&TEXT(ABS(F45)*B21,"##,##0"),"↑ Increase by ₹"&TEXT(ABS(F45)*B21,"##,##0"))) -> ↑ Increase by ₹2,025,500
A46: Debt | B46: =SUMPRODUCT((B6:B17="Yes")*(D6:D17="Debt")*E6:E17) -> 860000 | C46: =SUMPRODUCT((B6:B17="Yes")*(D6:D17="Debt")*S6:S17) -> 3804258.9 | D46: =IF(B21<>0,B46/B21,0) -> 0.20899149 | E46: =Assumptions_Config!D58 -> 0.1 | F46: =D46-E46 -> 0.10899149 | G46: =IF(ABS(F46)<0.02,"✅ On target",IF(F46>0,"↓ Reduce by ₹"&TEXT(ABS(F46)*B21,"##,##0"),"↑ Increase by ₹"&TEXT(ABS(F46)*B21,"##,##0"))) -> ↓ Reduce by ₹448,500
A47: Other | B47: =SUMPRODUCT((B6:B17="Yes")*(D6:D17="Other")*E6:E17) -> 2400000 | C47: =SUMPRODUCT((B6:B17="Yes")*(D6:D17="Other")*S6:S17) -> 7910899.6 | D47: =IF(B21<>0,B47/B21,0) -> 0.58323208 | E47: =Assumptions_Config!D59 -> 0.2 | F47: =D47-E47 -> 0.38323208 | G47: =IF(ABS(F47)<0.02,"✅ On target",IF(F47>0,"↓ Reduce by ₹"&TEXT(ABS(F47)*B21,"##,##0"),"↑ Increase by ₹"&TEXT(ABS(F47)*B21,"##,##0"))) -> ↓ Reduce by ₹1,577,000
A50: D. SCENARIO OUTPUTS
A51: Scenario | B51: Mult | C51: Pre-Tax | D51: Post-Tax | E51: Real NW | F51: Gains | G51: Tax | H51: Drag%
A52: Optimistic | B52: =Assumptions_Config!D22 -> 1.15 | C52: =B25+B26*B52 -> 28786392 | D52: =C52-MAX(C52-B25,0)*Assumptions_Config!H22 -> 23517044 | E52: =D52/(1+Assumptions_Config!G22)^Assumptions_Config!$D$8 -> 5629793.4 | F52: =MAX(C52-B25,0) -> 21077392 | G52: =C52-D52 -> 5269348.1 | H52: =IF(D52<>0,(D52-E52)/D52,0) -> 0.76060795
A53: Mod. Optimistic | B53: =Assumptions_Config!D23 -> 1.07 | C53: =B25+B26*B53 -> 27320139 | D53: =C53-MAX(C53-B25,0)*Assumptions_Config!H23 -> 22417354 | E53: =D53/(1+Assumptions_Config!G23)^Assumptions_Config!$D$8 -> 5366536.4 | F53: =MAX(C53-B25,0) -> 19611139 | G53: =C53-D53 -> 4902784.8 | H53: =IF(D53<>0,(D53-E53)/D53,0) -> 0.76060795
A54: Base Case | B54: =Assumptions_Config!D24 -> 1 | C54: =B25+B26*B54 -> 26037167 | D54: =C54-MAX(C54-B25,0)*Assumptions_Config!H24 -> 21455125 | E54: =D54/(1+Assumptions_Config!G24)^Assumptions_Config!$D$8 -> 5136186.5 | F54: =MAX(C54-B25,0) -> 18328167 | G54: =C54-D54 -> 4582041.8 | H54: =IF(D54<>0,(D54-E54)/D54,0) -> 0.76060795
A55: Mod. Conservative | B55: =Assumptions_Config!D25 -> 0.9 | C55: =B25+B26*B55 -> 24204351 | D55: =C55-MAX(C55-B25,0)*Assumptions_Config!H25 -> 20080513 | E55: =D55/(1+Assumptions_Config!G25)^Assumptions_Config!$D$8 -> 4807115.1 | F55: =MAX(C55-B25,0) -> 16495351 | G55: =C55-D55 -> 4123837.6 | H55: =IF(D55<>0,(D55-E55)/D55,0) -> 0.76060795
A56: Conservative | B56: =Assumptions_Config!D26 -> 0.8 | C56: =B25+B26*B56 -> 22371534 | D56: =C56-MAX(C56-B25,0)*Assumptions_Config!H26 -> 18705900 | E56: =D56/(1+Assumptions_Config!G26)^Assumptions_Config!$D$8 -> 4478043.8 | F56: =MAX(C56-B25,0) -> 14662534 | G56: =C56-D56 -> 3665633.5 | H56: =IF(D56<>0,(D56-E56)/D56,0) -> 0.76060795
A59: E. YEAR-BY-YEAR
A60: Yr | B60: Year | C60: Nominal | D60: Post-Tax | E60: Real | F60: Expenses | G60: Net
A61: 0 | B61: 2026 | C61: =B21 -> 4115000 | D61: =B21 -> 4115000 | E61: =B21 -> 4115000 | F61: =SUMPRODUCT((Major_Expenses!D5:D9<=2026)*Major_Expenses!J5:J9) -> 0 | G61: =D61-F61 -> 4115000
A62: 1 | B62: 2027 | C62: =IF(Assumptions_Config!$D$8=0,B21,B21*(B22/B21)^(A62/Assumptions_Config!$D$8)) -> 4653554.1 | D62: =IF(Assumptions_Config!$D$8=0,B21,B21*(B23/B21)^(A62/Assumptions_Config!$D$8)) -> 4606448.4 | E62: =D62/(1+Assumptions_Config!$D$5)^A62 -> 4187680.4 | F62: =SUMPRODUCT((Major_Expenses!D5:D9<=2027)*Major_Expenses!J5:J9) -> 550000 | G62: =D62-F62 -> 4056448.4
A63: 2 | B63: 2028 | C63: =IF(Assumptions_Config!$D$8=0,B21,B21*(B22/B21)^(A63/Assumptions_Config!$D$8)) -> 5262591.9 | D63: =IF(Assumptions_Config!$D$8=0,B21,B21*(B23/B21)^(A63/Assumptions_Config!$D$8)) -> 5156589.7 | E63: =D63/(1+Assumptions_Config!$D$5)^A63 -> 4261644.4 | F63: =SUMPRODUCT((Major_Expenses!D5:D9<=2028)*Major_Expenses!J5:J9) -> 3575000 | G63: =D63-F63 -> 1581589.7
A64: 3 | B64: 2029 | C64: =IF(Assumptions_Config!$D$8=0,B21,B21*(B22/B21)^(A64/Assumptions_Config!$D$8)) -> 5951338 | D64: =IF(Assumptions_Config!$D$8=0,B21,B21*(B23/B21)^(A64/Assumptions_Config!$D$8)) -> 5772433.6 | E64: =D64/(1+Assumptions_Config!$D$5)^A64 -> 4336914.8 | F64: =SUMPRODUCT((Major_Expenses!D5:D9<=2029)*Major_Expenses!J5:J9) -> 3575000 | G64: =D64-F64 -> 2197433.6
A65: 4 | B65: 2030 | C65: =IF(Assumptions_Config!$D$8=0,B21,B21*(B22/B21)^(A65/Assumptions_Config!$D$8)) -> 6730224.4 | D65: =IF(Assumptions_Config!$D$8=0,B21,B21*(B23/B21)^(A65/Assumptions_Config!$D$8)) -> 6461826.9 | E65: =D65/(1+Assumptions_Config!$D$5)^A65 -> 4413514.7 | F65: =SUMPRODUCT((Major_Expenses!D5:D9<=2030)*Major_Expenses!J5:J9) -> 5075000 | G65: =D65-F65 -> 1386826.9
A66: 5 | B66: 2031 | C66: =IF(Assumptions_Config!$D$8=0,B21,B21*(B22/B21)^(A66/Assumptions_Config!$D$8)) -> 7611048.2 | D66: =IF(Assumptions_Config!$D$8=0,B21,B21*(B23/B21)^(A66/Assumptions_Config!$D$8)) -> 7233553.3 | E66: =D66/(1+Assumptions_Config!$D$5)^A66 -> 4491467.5 | F66: =SUMPRODUCT((Major_Expenses!D5:D9<=2031)*Major_Expenses!J5:J9) -> 5075000 | G66: =D66-F66 -> 2158553.3
A67: 6 | B67: 2032 | C67: =IF(Assumptions_Config!$D$8=0,B21,B21*(B22/B21)^(A67/Assumptions_Config!$D$8)) -> 8607150.5 | D67: =IF(Assumptions_Config!$D$8=0,B21,B21*(B23/B21)^(A67/Assumptions_Config!$D$8)) -> 8097446 | E67: =D67/(1+Assumptions_Config!$D$5)^A67 -> 4570797.1 | F67: =SUMPRODUCT((Major_Expenses!D5:D9<=2032)*Major_Expenses!J5:J9) -> 8618122 | G67: =D67-F67 -> -520676.04
A68: 7 | B68: 2033 | C68: =IF(Assumptions_Config!$D$8=0,B21,B21*(B22/B21)^(A68/Assumptions_Config!$D$8)) -> 9733618.6 | D68: =IF(Assumptions_Config!$D$8=0,B21,B21*(B23/B21)^(A68/Assumptions_Config!$D$8)) -> 9064512 | E68: =D68/(1+Assumptions_Config!$D$5)^A68 -> 4651527.9 | F68: =SUMPRODUCT((Major_Expenses!D5:D9<=2033)*Major_Expenses!J5:J9) -> 8618122 | G68: =D68-F68 -> 446390
A69: 8 | B69: 2034 | C69: =IF(Assumptions_Config!$D$8=0,B21,B21*(B22/B21)^(A69/Assumptions_Config!$D$8)) -> 11007514 | D69: =IF(Assumptions_Config!$D$8=0,B21,B21*(B23/B21)^(A69/Assumptions_Config!$D$8)) -> 10147073 | E69: =D69/(1+Assumptions_Config!$D$5)^A69 -> 4733684.6 | F69: =SUMPRODUCT((Major_Expenses!D5:D9<=2034)*Major_Expenses!J5:J9) -> 8618122 | G69: =D69-F69 -> 1528951.3
A70: 9 | B70: 2035 | C70: =IF(Assumptions_Config!$D$8=0,B21,B21*(B22/B21)^(A70/Assumptions_Config!$D$8)) -> 12448132 | D70: =IF(Assumptions_Config!$D$8=0,B21,B21*(B23/B21)^(A70/Assumptions_Config!$D$8)) -> 11358923 | E70: =D70/(1+Assumptions_Config!$D$5)^A70 -> 4817292.3 | F70: =SUMPRODUCT((Major_Expenses!D5:D9<=2035)*Major_Expenses!J5:J9) -> 15691965 | G70: =D70-F70 -> -4333041.8
A71: 10 | B71: 2036 | C71: =IF(Assumptions_Config!$D$8=0,B21,B21*(B22/B21)^(A71/Assumptions_Config!$D$8)) -> 14077291 | D71: =IF(Assumptions_Config!$D$8=0,B21,B21*(B23/B21)^(A71/Assumptions_Config!$D$8)) -> 12715503 | E71: =D71/(1+Assumptions_Config!$D$5)^A71 -> 4902376.8 | F71: =SUMPRODUCT((Major_Expenses!D5:D9<=2036)*Major_Expenses!J5:J9) -> 15691965 | G71: =D71-F71 -> -2976462.3
A72: 11 | B72: 2037 | C72: =IF(Assumptions_Config!$D$8=0,B21,B21*(B22/B21)^(A72/Assumptions_Config!$D$8)) -> 15919669 | D72: =IF(Assumptions_Config!$D$8=0,B21,B21*(B23/B21)^(A72/Assumptions_Config!$D$8)) -> 14234097 | E72: =D72/(1+Assumptions_Config!$D$5)^A72 -> 4988964 | F72: =SUMPRODUCT((Major_Expenses!D5:D9<=2037)*Major_Expenses!J5:J9) -> 15691965 | G72: =D72-F72 -> -1457868.5
A73: 12 | B73: 2038 | C73: =IF(Assumptions_Config!$D$8=0,B21,B21*(B22/B21)^(A73/Assumptions_Config!$D$8)) -> 18003169 | D73: =IF(Assumptions_Config!$D$8=0,B21,B21*(B23/B21)^(A73/Assumptions_Config!$D$8)) -> 15934054 | E73: =D73/(1+Assumptions_Config!$D$5)^A73 -> 5077080.6 | F73: =SUMPRODUCT((Major_Expenses!D5:D9<=2038)*Major_Expenses!J5:J9) -> 15691965 | G73: =D73-F73 -> 242088.65
A74: 13 | B74: 2039 | C74: =IF(Assumptions_Config!$D$8=0,B21,B21*(B22/B21)^(A74/Assumptions_Config!$D$8)) -> 20359349 | D74: =IF(Assumptions_Config!$D$8=0,B21,B21*(B23/B21)^(A74/Assumptions_Config!$D$8)) -> 17837034 | E74: =D74/(1+Assumptions_Config!$D$5)^A74 -> 5166753.5 | F74: =SUMPRODUCT((Major_Expenses!D5:D9<=2039)*Major_Expenses!J5:J9) -> 15691965 | G74: =D74-F74 -> 2145069.2
A75: 14 | B75: 2040 | C75: =IF(Assumptions_Config!$D$8=0,B21,B21*(B22/B21)^(A75/Assumptions_Config!$D$8)) -> 23023896 | D75: =IF(Assumptions_Config!$D$8=0,B21,B21*(B23/B21)^(A75/Assumptions_Config!$D$8)) -> 19967285 | E75: =D75/(1+Assumptions_Config!$D$5)^A75 -> 5258010.2 | F75: =SUMPRODUCT((Major_Expenses!D5:D9<=2040)*Major_Expenses!J5:J9) -> 15691965 | G75: =D75-F75 -> 4275319.9
A76: 15 | B76: 2041 | C76: =IF(Assumptions_Config!$D$8=0,B21,B21*(B22/B21)^(A76/Assumptions_Config!$D$8)) -> 26037167 | D76: =IF(Assumptions_Config!$D$8=0,B21,B21*(B23/B21)^(A76/Assumptions_Config!$D$8)) -> 22351948 | E76: =D76/(1+Assumptions_Config!$D$5)^A76 -> 5350878.7 | F76: =SUMPRODUCT((Major_Expenses!D5:D9<=2041)*Major_Expenses!J5:J9) -> 15691965 | G76: =D76-F76 -> 6659983.3
A77: 16 | B77: 2042 | C77: =IF(Assumptions_Config!$D$8=0,B21,B21*(B22/B21)^(A77/Assumptions_Config!$D$8)) -> 29444803 | D77: =IF(Assumptions_Config!$D$8=0,B21,B21*(B23/B21)^(A77/Assumptions_Config!$D$8)) -> 25021409 | E77: =D77/(1+Assumptions_Config!$D$5)^A77 -> 5445387.5 | F77: =SUMPRODUCT((Major_Expenses!D5:D9<=2042)*Major_Expenses!J5:J9) -> 15691965 | G77: =D77-F77 -> 9329443.6
A78: 17 | B78: 2043 | C78: =IF(Assumptions_Config!$D$8=0,B21,B21*(B22/B21)^(A78/Assumptions_Config!$D$8)) -> 33298417 | D78: =IF(Assumptions_Config!$D$8=0,B21,B21*(B23/B21)^(A78/Assumptions_Config!$D$8)) -> 28009679 | E78: =D78/(1+Assumptions_Config!$D$5)^A78 -> 5541565.6 | F78: =SUMPRODUCT((Major_Expenses!D5:D9<=2043)*Major_Expenses!J5:J9) -> 15691965 | G78: =D78-F78 -> 12317714
A79: 18 | B79: 2044 | C79: =IF(Assumptions_Config!$D$8=0,B21,B21*(B22/B21)^(A79/Assumptions_Config!$D$8)) -> 37656375 | D79: =IF(Assumptions_Config!$D$8=0,B21,B21*(B23/B21)^(A79/Assumptions_Config!$D$8)) -> 31354833 | E79: =D79/(1+Assumptions_Config!$D$5)^A79 -> 5639442.4 | F79: =SUMPRODUCT((Major_Expenses!D5:D9<=2044)*Major_Expenses!J5:J9) -> 15691965 | G79: =D79-F79 -> 15662868
A80: 19 | B80: 2045 | C80: =IF(Assumptions_Config!$D$8=0,B21,B21*(B22/B21)^(A80/Assumptions_Config!$D$8)) -> 42584685 | D80: =IF(Assumptions_Config!$D$8=0,B21,B21*(B23/B21)^(A80/Assumptions_Config!$D$8)) -> 35099495 | E80: =D80/(1+Assumptions_Config!$D$5)^A80 -> 5739047.9 | F80: =SUMPRODUCT((Major_Expenses!D5:D9<=2045)*Major_Expenses!J5:J9) -> 15691965 | G80: =D80-F80 -> 19407530
A81: 20 | B81: 2046 | C81: =IF(Assumptions_Config!$D$8=0,B21,B21*(B22/B21)^(A81/Assumptions_Config!$D$8)) -> 48157991 | D81: =IF(Assumptions_Config!$D$8=0,B21,B21*(B23/B21)^(A81/Assumptions_Config!$D$8)) -> 39291376 | E81: =D81/(1+Assumptions_Config!$D$5)^A81 -> 5840412.6 | F81: =SUMPRODUCT((Major_Expenses!D5:D9<=2046)*Major_Expenses!J5:J9) -> 15691965 | G81: =D81-F81 -> 23599411
A84: F. RETIREMENT ADEQUACY
A86: Years to Retirement | B86: =Assumptions_Config!$D$14-Assumptions_Config!$D$15 -> 10
A87: Years in Retirement | B87: =Assumptions_Config!$D$16-Assumptions_Config!$D$14 -> 15
A88: Monthly Expense at Retirement | B88: =Assumptions_Config!$D$12*(1+Assumptions_Config!$D$5)^B86 -> 129687.12
A89: Annual Expense at Retirement | B89: =B88*12 -> 1556245.5
A90: Required Retirement Corpus | B90: =B89*((1-(1+Assumptions_Config!$D$65)^(-B87))/Assumptions_Config!$D$65) -> 18578357
A91: Projected Corpus at Retirement | B91: =B23 -> 22351948
A92: Retirement SURPLUS / GAP | B92: =B91-B90 -> 3773590.9
A93: Retirement Readiness % | B93: =IF(B90=0,0,MIN(B91/B90,1.5)) -> 1.2031176
A96: G. STRESS TEST RESULTS
A97: Event | B97: Equity Loss | C97: Debt Loss | D97: Gold Change | E97: Portfolio Impact | F97: Recovery Years
A98: =Assumptions_Config!C48 -> 2008 Crisis | B98: =Assumptions_Config!D48 -> -0.52 | C98: =Assumptions_Config!E48 -> -0.05 | D98: =Assumptions_Config!F48 -> 0.25 | E98: =B21*(B98*D45+C98*D46+D98*D47) -> 112400 | F98: =IF(E98>=0,0,IFERROR(LOG(1-E98/B21)/LOG(1+Assumptions_Config!$D$64),99)) -> 0
A99: =Assumptions_Config!C49 -> COVID 2020 | B99: =Assumptions_Config!D49 -> -0.38 | C99: =Assumptions_Config!E49 -> -0.02 | D99: =Assumptions_Config!F49 -> 0.15 | E99: =B21*(B99*D45+C99*D46+D99*D47) -> 17900 | F99: =IF(E99>=0,0,IFERROR(LOG(1-E99/B21)/LOG(1+Assumptions_Config!$D$64),99)) -> 0
A100: =Assumptions_Config!C50 -> 2013 Taper | B100: =Assumptions_Config!D50 -> -0.25 | C100: =Assumptions_Config!E50 -> -0.08 | D100: =Assumptions_Config!F50 -> -0.1 | E100: =B21*(B100*D45+C100*D46+D100*D47) -> -522550 | F100: =IF(E100>=0,0,IFERROR(LOG(1-E100/B21)/LOG(1+Assumptions_Config!$D$64),99)) -> 1.054873
A101: =Assumptions_Config!C51 -> Inflation Spike | B101: =Assumptions_Config!D51 -> -0.15 | C101: =Assumptions_Config!E51 -> -0.1 | D101: =Assumptions_Config!F51 -> 0.2 | E101: =B21*(B101*D45+C101*D46+D101*D47) -> 265750 | F101: =IF(E101>=0,0,IFERROR(LOG(1-E101/B21)/LOG(1+Assumptions_Config!$D$64),99)) -> 0
A102: =Assumptions_Config!C52 -> Custom | B102: =Assumptions_Config!D52 -> -0.3 | C102: =Assumptions_Config!E52 -> -0.05 | D102: =Assumptions_Config!F52 -> 0.1 | E102: =B21*(B102*D45+C102*D46+D102*D47) -> -59500 | F102: =IF(E102>=0,0,IFERROR(LOG(1-E102/B21)/LOG(1+Assumptions_Config!$D$64),99)) -> 0.12667364

Sheet What_If_Builder
A1: WHAT-IF SCENARIO BUILDER
A2: Compare current plan vs hypothetical changes
A4: WHAT-IF SCENARIOS
A5: What If... | B5: Change Amount | C5: Current Plan NW | D5: What-If NW | E5: Impact ₹ | F5: Impact % | H5: Scenario driver note: All what-if assumptions now reference Assumptions_Config model drivers instead of hardcoded constants.
A6: Increase SIP by ₹5,000/month | B6: 5000 | C6: =Helper_Calcs!B23 -> 22351948 | D6: =C6+B6*((1+Assumptions_Config!$D$64/12)^(Assumptions_Config!$D$8*12)-1)/(Assumptions_Config!$D$64/12)*(1-Assumptions_Config!$D$6) -> 24225374 | E6: =D6-C6 -> 1873425.7 | F6: =IF(C6=0,0,E6/C6) -> 0.083814874
A7: Add ₹10,00,000 lump sum today | B7: 1000000 | C7: =Helper_Calcs!B23 -> 22351948 | D7: =C7+B7*(1+Assumptions_Config!$D$64)^Assumptions_Config!$D$8*(1-Assumptions_Config!$D$6) -> 26457123 | E7: =D7-C7 -> 4105174.3 | F7: =IF(C7=0,0,E7/C7) -> 0.18366069
A8: Stop all SIPs for 2 years | B8: 0 | C8: =Helper_Calcs!B23 -> 22351948 | D8: =C8-Helper_Calcs!B35*24*(1+Assumptions_Config!$D$64)^(Assumptions_Config!$D$8-2) -> 19524405 | E8: =D8-C8 -> -2827543.5 | F8: =IF(C8=0,0,E8/C8) -> -0.12650099
A9: Retire 5 years earlier | B9: 0 | C9: =Helper_Calcs!B23 -> 22351948 | D9: =C9*(1+Assumptions_Config!$D$66) -> 19669715 | E9: =D9-C9 -> -2682233.8 | F9: =IF(C9=0,0,E9/C9) -> -0.12
A10: Inflation is 10% instead of 8% | B10: 0 | C10: =Helper_Calcs!B23 -> 22351948 | D10: =C10*(1+Assumptions_Config!$D$67) -> 20787312 | E10: =D10-C10 -> -1564636.4 | F10: =IF(C10=0,0,E10/C10) -> -0.07
A11: Increase step-up to 15% | B11: 0 | C11: =Helper_Calcs!B23 -> 22351948 | D11: =C11*(1+Assumptions_Config!$D$68) -> 23469546 | E11: =D11-C11 -> 1117597.4 | F11: =IF(C11=0,0,E11/C11) -> 0.05

Sheet Financial_Scorecard
A1: FINANCIAL HEALTH SCORECARD
A2: 10-Dimension Assessment | Auto-Scored from Your Data
A4: HEALTH DIMENSIONS (0-10 each)
A5: # | B5: Dimension | C5: Score | D5: Max | E5: Status | F5: Recommendation
A6: 1 | B6: Savings Rate | C6: =IF(Income_Expenses!B33>0.3,10,IF(Income_Expenses!B33>0.2,7,IF(Income_Expenses!B33>0.1,5,3))) -> 10 | D6: 10 | E6: =IF(C6>=8,"🟢 Strong",IF(C6>=5,"🟡 Fair","🔴 Weak")) -> 🟢 Strong | F6: Save 20%+ of income
A7: 2 | B7: Emergency Fund | C7: =IF(Helper_Calcs!B38>1,10,IF(Helper_Calcs!B38>0.7,7,IF(Helper_Calcs!B38>0.4,4,2))) -> 7 | D7: 10 | E7: =IF(C7>=8,"🟢 Strong",IF(C7>=5,"🟡 Fair","🔴 Weak")) -> 🟡 Fair | F7: Build 6 months expenses
A8: 3 | B8: Debt Health | C8: =IF(Debt_Tracker!C15>1,2,IF(Debt_Tracker!C15>0.5,5,IF(Debt_Tracker!C15>0.2,7,9))) -> 2 | D8: 10 | E8: =IF(C8>=8,"🟢 Strong",IF(C8>=5,"🟡 Fair","🔴 Weak")) -> 🔴 Weak | F8: Keep debt-to-income <40%
A9: 4 | B9: Insurance Cover | C9: =IF(Insurance_Summary!B14<=0,9,IF(Insurance_Summary!B14<5000000,6,3)) -> 3 | D9: 10 | E9: =IF(C9>=8,"🟢 Strong",IF(C9>=5,"🟡 Fair","🔴 Weak")) -> 🔴 Weak | F9: 10× income life cover
A10: 5 | B10: Diversification | C10: =IF(Investment_Input!J5<0.3,9,IF(Investment_Input!J5<0.5,6,3)) -> 6 | D10: 10 | E10: =IF(C10>=8,"🟢 Strong",IF(C10>=5,"🟡 Fair","🔴 Weak")) -> 🟡 Fair | F10: No single asset >25%
A11: 6 | B11: Tax Efficiency | C11: =IF(COUNTIF(Investment_Input!AA9:AA28,"No")>2,8,IF(COUNTIF(Investment_Input!AA9:AA28,"No")>0,5,3)) -> 8 | D11: 10 | E11: =IF(C11>=8,"🟢 Strong",IF(C11>=5,"🟡 Fair","🔴 Weak")) -> 🟢 Strong | F11: Use 80C, NPS, PPF
A12: 7 | B12: Retirement Ready | C12: =MIN(Helper_Calcs!B93*10,10) -> 10 | D12: 10 | E12: =IF(C12>=8,"🟢 Strong",IF(C12>=5,"🟡 Fair","🔴 Weak")) -> 🟢 Strong | F12: Target 100% funded
A13: 8 | B13: Goal Funding | C13: =AVERAGE(Goals_Tracker!J5:J9)*10 -> 1.8450961 | D13: 10 | E13: =IF(C13>=8,"🟢 Strong",IF(C13>=5,"🟡 Fair","🔴 Weak")) -> 🔴 Weak | F13: All goals on track
A14: 9 | B14: Risk Alignment | C14: =IF(ABS(Helper_Calcs!B39-6)<2,8,IF(ABS(Helper_Calcs!B39-6)<4,5,3)) -> 8 | D14: 10 | E14: =IF(C14>=8,"🟢 Strong",IF(C14>=5,"🟡 Fair","🔴 Weak")) -> 🟢 Strong | F14: Match risk to profile
A15: 10 | B15: Liquidity | C15: =IF(Helper_Calcs!B38>1,9,IF(Helper_Calcs!B38>0.5,6,3)) -> 6 | D15: 10 | E15: =IF(C15>=8,"🟢 Strong",IF(C15>=5,"🟡 Fair","🔴 Weak")) -> 🟡 Fair | F15: Adequate liquid assets
A17: =(C6*0.1+C7*0.15+C8*0.1+C9*0.15+C10*0.08+C11*0.07+C12*0.15+C13*0.1+C14*0.05+C15*0.05)*10 -> 61.245096 | D17: WEIGHTED SCORE (out of 100)
D18: =IF(A17>=80,"🟢 EXCELLENT — Strong advisory position",IF(A17>=60,"🟡 GOOD — Improve a few key gaps",IF(A17>=40,"🟠 FAIR — Priority actions required","🔴 NEEDS ATTENTION — Close protection/liquidity gaps first"))) -> 🟡 GOOD — Improve a few key gaps
A21: PRIORITY ACTION ITEMS
A22: # | B22: Action | C22: Priority | D22: Impact | E22: Status
A23: 1 | B23: Build emergency fund to 6 months | C23: 🔴 HIGH | D23: Safety | E23: ☐ Pending
A24: 2 | B24: Increase term life cover | C24: 🔴 HIGH | D24: Risk | E24: ☐ Pending
A25: 3 | B25: Pay off high-interest debt first | C25: 🟡 MED | D25: Savings | E25: ☐ Pending
A26: 4 | B26: Start ELSS SIP for 80C benefit | C26: 🟡 MED | D26: Tax | E26: ☐ Pending
A27: 5 | B27: Rebalance: align to target allocation | C27: 🟢 LOW | D27: Returns | E27: ☐ Pending
A28: 6 | B28: Review insurance annually | C28: 🟢 LOW | D28: Risk | E28: ☐ Pending
A29: 7 | B29: Increase SIP step-up to 10%+ | C29: 🟡 MED | D29: Growth | E29: ☐ Pending
A30: 8 | B30: Diversify: reduce concentration risk | C30: 🟡 MED | D30: Risk | E30: ☐ Pending

Sheet Advisor_Dashboard
A1: ADVISOR DASHBOARD — COMPLETE ANALYTICS
A2: Updated: 18-Mar-2026 | Industry-standard refresh | Focus: gaps, actions, comparatives
A3: Horizon: | B3: =Assumptions_Config!$D$8 -> 15 | D3: Unit: | E3: =Assumptions_Config!$D$7 -> Lakhs | G3: Inflation: | H3: =Assumptions_Config!$D$5 -> 0.1 | J3: Tax: | K3: =Assumptions_Config!$D$6 -> 0.25 | M3: Risk: | N3: =Helper_Calcs!B40 -> Moderate
A5: TRUE NET WORTH | D5: PROJECTED POST-TAX | G5: GOAL FUNDING % | J5: RETIREMENT READY | M5: EMERGENCY RATIO | P5: FUNDING GAP
A6: =Helper_Calcs!B30/Helper_Calcs!B41 -> #NAME? | D6: =Helper_Calcs!B23/Helper_Calcs!B41 -> #NAME? | G6: =AVERAGE(Goals_Tracker!J5:J9) -> 0.18450961 | J6: =Helper_Calcs!B93 -> 1.2031176 | M6: =Helper_Calcs!B38 -> 1 | P6: =IF(Helper_Calcs!B32<0,ABS(Helper_Calcs!B32)/Helper_Calcs!B41,0) -> 0
A9: ="In "&Helper_Calcs!B42 -> In Lakhs | D9: ="Base case • "&Helper_Calcs!B42 -> Base case • Lakhs | G9: Across all goals | J9: Target 100% | M9: Target 1.0x | P9: After major expenses
A11: Monthly SIP | D11: Debt / Income | G11: Life Cover Gap | J11: Max Concentration | M11: Wtd Risk Score | P11: Health Score
A12: =Helper_Calcs!B35/Helper_Calcs!B41 -> #NAME? | D12: =Debt_Tracker!C15 -> 2.3527778 | G12: =MAX(Insurance_Summary!B15,0)/Helper_Calcs!B41 -> #NAME? | J12: =Investment_Input!J5 -> 0.48602673 | M12: =Helper_Calcs!B39 -> 5.2867558 | P12: =Financial_Scorecard!A17 -> 61.245096
A14: ALLOCATION & REBALANCING
A15: Bucket | B15: Current | C15: Target | D15: Deviation | E15: Action | H15: TOP PRIORITIES
A16: Equity | B16: =Helper_Calcs!D45 -> 0.20777643 | C16: =Helper_Calcs!E45 -> 0.7 | D16: =Helper_Calcs!F45 -> -0.49222357 | E16: =Helper_Calcs!G45 -> ↑ Increase by ₹2,025,500 | H16: =IF(Helper_Calcs!B32<0,"1) Close funding gap of "&TEXT(ABS(Helper_Calcs!B32)/Helper_Calcs!B41,"#,##0.0")&" "&Helper_Calcs!B42&" after future expenses","1) No funding gap after future expenses") -> 1) No funding gap after future expenses
A17: Debt | B17: =Helper_Calcs!D46 -> 0.20899149 | C17: =Helper_Calcs!E46 -> 0.1 | D17: =Helper_Calcs!F46 -> 0.10899149 | E17: =Helper_Calcs!G46 -> ↓ Reduce by ₹448,500 | H17: =IF(Insurance_Summary!B15>0,"2) Increase life cover by "&TEXT(Insurance_Summary!B15/Helper_Calcs!B41,"#,##0.0")&" "&Helper_Calcs!B42,"2) Life cover is adequate") -> #NAME?
A18: Other | B18: =Helper_Calcs!D47 -> 0.58323208 | C18: =Helper_Calcs!E47 -> 0.2 | D18: =Helper_Calcs!F47 -> 0.38323208 | E18: =Helper_Calcs!G47 -> ↓ Reduce by ₹1,577,000 | H18: =IF(ABS(Helper_Calcs!F45)>=ABS(Helper_Calcs!F46),IF(ABS(Helper_Calcs!F45)>=ABS(Helper_Calcs!F47),"3) Rebalance: "&Helper_Calcs!G45,"3) Rebalance: "&Helper_Calcs!G47),IF(ABS(Helper_Calcs!F46)>=ABS(Helper_Calcs!F47),"3) Rebalance: "&Helper_Calcs!G46,"3) Rebalance: "&Helper_Calcs!G47)) -> 3) Rebalance: ↑ Increase by ₹2,025,500
A20: ="SCENARIO COMPARISON ("&Helper_Calcs!B42&")" -> SCENARIO COMPARISON (Lakhs)
A21: Scenario | B21: Post-Tax | C21: Real NW | D21: Drag%
A22: Optimistic | B22: =Helper_Calcs!D52/Helper_Calcs!B41 -> #NAME? | C22: =Helper_Calcs!E52/Helper_Calcs!B41 -> #NAME? | D22: =Helper_Calcs!H52 -> 0.76060795
A23: Mod. Optimistic | B23: =Helper_Calcs!D53/Helper_Calcs!B41 -> #NAME? | C23: =Helper_Calcs!E53/Helper_Calcs!B41 -> #NAME? | D23: =Helper_Calcs!H53 -> 0.76060795
A24: Base Case | B24: =Helper_Calcs!D54/Helper_Calcs!B41 -> #NAME? | C24: =Helper_Calcs!E54/Helper_Calcs!B41 -> #NAME? | D24: =Helper_Calcs!H54 -> 0.76060795
A25: Mod. Conservative | B25: =Helper_Calcs!D55/Helper_Calcs!B41 -> #NAME? | C25: =Helper_Calcs!E55/Helper_Calcs!B41 -> #NAME? | D25: =Helper_Calcs!H55 -> 0.76060795
A26: Conservative | B26: =Helper_Calcs!D56/Helper_Calcs!B41 -> #NAME? | C26: =Helper_Calcs!E56/Helper_Calcs!B41 -> #NAME? | D26: =Helper_Calcs!H56 -> 0.76060795
A28: CHARTS

Sheet Client_Dashboard
A1: Siddharth Tiwari
A2: WEALTH ADVISORY — EXECUTIVE SUMMARY
A3: Date: 18 March 2026 | Confidential
A5: Client: | D5: =Assumptions_Config!$D$18 -> [Enter Client Name]
A7: TRUE NET WORTH | G7: PROJECTED POST-TAX | M7: RETIREMENT READY
A8: =Helper_Calcs!B30/Helper_Calcs!B41 -> #NAME? | G8: =Helper_Calcs!B23/Helper_Calcs!B41 -> #NAME? | M8: =Helper_Calcs!B93 -> 1.2031176
A11: ="In "&Helper_Calcs!B42 -> In Lakhs | G11: ="Base case • "&Helper_Calcs!B42 -> Base case • Lakhs | M11: Target 100%
A13: Goal Funding % | D13: Emergency Ratio | G13: Life Cover Gap | J13: Debt / Income | M13: Health Score | P13: Monthly SIP
A14: =AVERAGE(Goals_Tracker!J5:J9) -> 0.18450961 | D14: =Helper_Calcs!B38 -> 1 | G14: =MAX(Insurance_Summary!B15,0)/Helper_Calcs!B41 -> #NAME? | J14: =Debt_Tracker!C15 -> 2.3527778 | M14: =Financial_Scorecard!A17 -> 61.245096 | P14: =Helper_Calcs!B35/Helper_Calcs!B41 -> #NAME?
A16: Executive focus: build protection first, close the funding gap, and rebalance toward target allocation. Review goal funding, retirement readiness, and liquidity before adding new risk.
A19: YOUR WEALTH PROJECTION
A37: ="SCENARIO & ALLOCATION ("&Helper_Calcs!B42&")" -> SCENARIO & ALLOCATION (Lakhs)
A38: Scenario | B38: Post-Tax NW | C38: Real NW
A39: Optimistic | B39: =Helper_Calcs!D52/Helper_Calcs!B41 -> #NAME? | C39: =Helper_Calcs!E52/Helper_Calcs!B41 -> #NAME?
A40: Mod. Optimistic | B40: =Helper_Calcs!D53/Helper_Calcs!B41 -> #NAME? | C40: =Helper_Calcs!E53/Helper_Calcs!B41 -> #NAME?
A41: Base Case | B41: =Helper_Calcs!D54/Helper_Calcs!B41 -> #NAME? | C41: =Helper_Calcs!E54/Helper_Calcs!B41 -> #NAME?
A42: Mod. Conservative | B42: =Helper_Calcs!D55/Helper_Calcs!B41 -> #NAME? | C42: =Helper_Calcs!E55/Helper_Calcs!B41 -> #NAME?
A43: Conservative | B43: =Helper_Calcs!D56/Helper_Calcs!B41 -> #NAME? | C43: =Helper_Calcs!E56/Helper_Calcs!B41 -> #NAME?
A54: Disclaimer: Projections based on assumed returns. Past performance ≠ future results. Market-linked investments subject to risk. Consult your advisor. Siddharth Tiwari | March 2026
